Workbook

Sheet 00_README
A1: AI Marketing Platform - Production Engineering Execution Workbook
A3: Purpose | B3: Executable production master backlog and control workbook for two engineers. S0-S8 deliver Production GA; S9-S10 are post-GA growth expansion.
A5: Architecture | B5: Modular Monolith + Durable Workers + Ports/Adapters + tenant-safe RLS
A6: Primary stack | B6: Nuxt 4.5.x + Nuxt UI v4 + Motion for Vue + Node.js 24 LTS + FastAPI/Python 3.14 + Supabase Auth/Postgres/Storage/Queues + OpenAI + Meta APIs
A7: Security baseline | B7: OWASP ASVS 5.0 L2-oriented + OWASP API Security Top 10 + tenant isolation tests
A8: Planning policy | B8: S0-S5 core delivery; S6 Marketing OS; S7 feature completeness; S8 GA hardening/launch; S9-S10 growth formats/automation. Release gates, not dates, define readiness.
A9: Estimate semantics | B9: Task hours include implementation + owner tests. Peer-review, planning, support and unplanned debugging are expected to consume remaining sprint capacity.
A12: Planning Controls - blue cells are user-changeable inputs
A14: Kickoff date | B14: 46272 | C14: Change this to rebase all sprint dates.
A15: Sprint length (calendar days) | B15: 14 | C15: 2-week sprint.
A16: Capacity / programmer / sprint (h) | B16: 80 | C16: Nominal 10 workdays x 8h; reserve is shown separately.
A17: Target planned utilization | B17: 0.85 | C17: Guideline, not a hard formula. Early integration sprints may be denser.
A18: Number of sprints | B18: 11 | C18: S8 is Production GA target; S9-S10 continue growth without changing core launch gates.
A20: Calculated planned release | B20: =$B$14+($B$15*$B$18)-1 -> 46425 | C20: External approvals (especially Meta) can move public launch even when engineering is complete.
A21: Production GA target (S8 end) | B21: =$B$14+($B$15*9)-1 -> 46397 | C21: Calendar target only; RG gates and Meta approval can still block public launch.
A23: Workbook workflow
A25: 1 | B25: Read 00_README + companion DOCX before implementation.
A26: 2 | B26: Use 01_ROADMAP for sprint outcomes/capacity; 02_BACKLOG is task source of truth.
A27: 3 | B27: Move Status through Not Started -> Ready -> In Progress -> In Review -> Done; use Blocked with note/evidence.
A28: 4 | B28: A task is Done only when Acceptance Criteria + Test Evidence + relevant Release Gate requirements are satisfied.
A29: 5 | B29: Do not delete postponed work. Mark Deferred and create explicit follow-up/reason.
A30: 6 | B30: Architecture/security/provider contract changes require ADR/update, not silent implementation drift.
A33: Color conventions
A35: Blue | B35: User-changeable inputs
A36: Black | B36: Formulas / derived values
A37: Green | B37: Linked/imported sources
A38: Gray | B38: Static constants / specification text
A39: Orange | B39: Review / caution / external dependency
A40: Light red | B40: Error / blocker / high risk
A41: Purple | B41: Control / architecture logic
A42: Teal | B42: KPI / key anchor
A44: Audit i kodit dhe scope-it — 2026-09-07
A45: Rishikim i thelluar: 133 skedarë first-party dhe 185 task-e. 02_BACKLOG: Y zbatimi, Z kryer, AA mbetur, AB pranim/prova të kërkuara, AC prova reale, AD kod/gjetje. 7 In Review, 106 In Progress, 35 Not Started, 2 Blocked, 35 Deferred, 0 Done.
A46: Progress 2026-09-07: 31 task-e partial u përditësuan me implementim dhe prova të reja; 0 u quajtën Done pa gates. 42/42 unit/integration dhe 8/8 E2E kaluan, bashkë me lint/types. 15_GJETJET J–K tregon statusin aktual të 17 gjetjeve.
A47: Progress 2026-09-08: 44 task-e partial u përditësuan me implementim dhe prova të reja; 0 u quajtën Done pa gates. 47/47 unit/integration dhe 8/8 E2E kaluan, bashkë me lint/types. 15_GJETJET J–K tregon statusin aktual të 17 gjetjeve.
A48: Code audit + S0-A03 implementation 2026-09-08: 24 task-e janë kryer në kod dhe presin pranim/gate; 90 janë pjesërisht të implementuara; 34 pa filluar; 35 deferred; 2 blocked; 0 Done. Shiko 02_BACKLOG AE–AJ dhe 16_HANDOFF_2_DEV.

Sheet 01_ROADMAP
A1: 22-Week Master Roadmap - 2 Engineers (Production GA at S8)
A2: Dates/estimates remain the original plan. Status audited 2026-09-07; S8/S9/S10 counters repaired. In Review is not production acceptance; release gates remain mandatory.
A4: Sprint | B4: Weeks | C4: Start | D4: End | E4: Outcome | F4: Primary Gates | G4: A Hours | H4: B Hours | I4: Total Hours | J4: Capacity | K4: Utilization | L4: Buffer Hours | M4: Open P0 | N4: Task Count | O4: Done | P4: Sprint Status
A5: S0 | B5: Weeks 1-2 | C5: ='00_README'!$B$14+(ROW()-5)*'00_README'!$B$15 -> 46272 | D5: =C5+'00_README'!$B$15-1 -> 46285 | E5: Foundation secure skeleton | F5: RG-01 / RG-02 / RG-03 / RG-17 | G5: =SUMIFS('02_BACKLOG'!$K:$K,'02_BACKLOG'!$B:$B,$A5,'02_BACKLOG'!$I:$I,"Programmer A") -> 71 | H5: =SUMIFS('02_BACKLOG'!$K:$K,'02_BACKLOG'!$B:$B,$A5,'02_BACKLOG'!$I:$I,"Programmer B") -> 71 | I5: =G5+H5 -> 142 | J5: ='00_README'!$B$16*2 -> 160 | K5: =IFERROR(I5/J5,0) -> 0.8875 | L5: =J5-I5 -> 18 | M5: =COUNTIFS('02_BACKLOG'!$B:$B,$A5,'02_BACKLOG'!$H:$H,"P0",'02_BACKLOG'!$L:$L,"<>Done",'02_BACKLOG'!$L:$L,"<>Deferred") -> 14 | N5: =COUNTIF('02_BACKLOG'!$B:$B,$A5) -> 18 | O5: =COUNTIFS('02_BACKLOG'!$B:$B,$A5,'02_BACKLOG'!$L:$L,"Done") -> 0 | P5: =IF(COUNTIFS('02_BACKLOG'!$B:$B,$A5,'02_BACKLOG'!$L:$L,"Deferred")=N5,"Deferred",IF(O5=N5,"Done",IF(COUNTIFS('02_BACKLOG'!$B:$B,$A5,'02_BACKLOG'!$L:$L,"In Progress")+COUNTIFS('02_BACKLOG'!$B:$B,$A5,'02_BACKLOG'!$L:$L,"In Review")>0,"In Progress",IF(COUNTIFS('02_BACKLOG'!$B:$B,$A5,'02_BACKLOG'!$L:$L,"Blocked")>0,"Blocked","Planned")))) -> In Progress
A6: S1 | B6: Weeks 3-4 | C6: ='00_README'!$B$14+(ROW()-5)*'00_README'!$B$15 -> 46286 | D6: =C6+'00_README'!$B$15-1 -> 46299 | E6: Organizations, RBAC, onboarding and Brand Brain | F6: RG-02 / RG-03 / RG-17 | G6: =SUMIFS('02_BACKLOG'!$K:$K,'02_BACKLOG'!$B:$B,$A6,'02_BACKLOG'!$I:$I,"Programmer A") -> 72 | H6: =SUMIFS('02_BACKLOG'!$K:$K,'02_BACKLOG'!$B:$B,$A6,'02_BACKLOG'!$I:$I,"Programmer B") -> 71 | I6: =G6+H6 -> 143 | J6: ='00_README'!$B$16*2 -> 160 | K6: =IFERROR(I6/J6,0) -> 0.89375 | L6: =J6-I6 -> 17 | M6: =COUNTIFS('02_BACKLOG'!$B:$B,$A6,'02_BACKLOG'!$H:$H,"P0",'02_BACKLOG'!$L:$L,"<>Done",'02_BACKLOG'!$L:$L,"<>Deferred") -> 9 | N6: =COUNTIF('02_BACKLOG'!$B:$B,$A6) -> 18 | O6: =COUNTIFS('02_BACKLOG'!$B:$B,$A6,'02_BACKLOG'!$L:$L,"Done") -> 0 | P6: =IF(COUNTIFS('02_BACKLOG'!$B:$B,$A6,'02_BACKLOG'!$L:$L,"Deferred")=N6,"Deferred",IF(O6=N6,"Done",IF(COUNTIFS('02_BACKLOG'!$B:$B,$A6,'02_BACKLOG'!$L:$L,"In Progress")+COUNTIFS('02_BACKLOG'!$B:$B,$A6,'02_BACKLOG'!$L:$L,"In Review")>0,"In Progress",IF(COUNTIFS('02_BACKLOG'!$B:$B,$A6,'02_BACKLOG'!$L:$L,"Blocked")>0,"Blocked","Planned")))) -> In Progress
A7: S2 | B7: Weeks 5-6 | C7: ='00_README'!$B$14+(ROW()-5)*'00_README'!$B$15 -> 46300 | D7: =C7+'00_README'!$B$15-1 -> 46313 | E7: Media pipeline and Meta connection | F7: RG-04 / RG-05 / RG-17 | G7: =SUMIFS('02_BACKLOG'!$K:$K,'02_BACKLOG'!$B:$B,$A7,'02_BACKLOG'!$I:$I,"Programmer A") -> 75 | H7: =SUMIFS('02_BACKLOG'!$K:$K,'02_BACKLOG'!$B:$B,$A7,'02_BACKLOG'!$I:$I,"Programmer B") -> 70 | I7: =G7+H7 -> 145 | J7: ='00_README'!$B$16*2 -> 160 | K7: =IFERROR(I7/J7,0) -> 0.90625 | L7: =J7-I7 -> 15 | M7: =COUNTIFS('02_BACKLOG'!$B:$B,$A7,'02_BACKLOG'!$H:$H,"P0",'02_BACKLOG'!$L:$L,"<>Done",'02_BACKLOG'!$L:$L,"<>Deferred") -> 15 | N7: =COUNTIF('02_BACKLOG'!$B:$B,$A7) -> 18 | O7: =COUNTIFS('02_BACKLOG'!$B:$B,$A7,'02_BACKLOG'!$L:$L,"Done") -> 0 | P7: =IF(COUNTIFS('02_BACKLOG'!$B:$B,$A7,'02_BACKLOG'!$L:$L,"Deferred")=N7,"Deferred",IF(O7=N7,"Done",IF(COUNTIFS('02_BACKLOG'!$B:$B,$A7,'02_BACKLOG'!$L:$L,"In Progress")+COUNTIFS('02_BACKLOG'!$B:$B,$A7,'02_BACKLOG'!$L:$L,"In Review")>0,"In Progress",IF(COUNTIFS('02_BACKLOG'!$B:$B,$A7,'02_BACKLOG'!$L:$L,"Blocked")>0,"Blocked","Planned")))) -> In Progress
A8: S3 | B8: Weeks 7-8 | C8: ='00_README'!$B$14+(ROW()-5)*'00_README'!$B$15 -> 46314 | D8: =C8+'00_README'!$B$15-1 -> 46327 | E8: Grounded AI creation and Content Studio | F8: RG-06 / RG-16 / RG-17 | G8: =SUMIFS('02_BACKLOG'!$K:$K,'02_BACKLOG'!$B:$B,$A8,'02_BACKLOG'!$I:$I,"Programmer A") -> 74 | H8: =SUMIFS('02_BACKLOG'!$K:$K,'02_BACKLOG'!$B:$B,$A8,'02_BACKLOG'!$I:$I,"Programmer B") -> 76 | I8: =G8+H8 -> 150 | J8: ='00_README'!$B$16*2 -> 160 | K8: =IFERROR(I8/J8,0) -> 0.9375 | L8: =J8-I8 -> 10 | M8: =COUNTIFS('02_BACKLOG'!$B:$B,$A8,'02_BACKLOG'!$H:$H,"P0",'02_BACKLOG'!$L:$L,"<>Done",'02_BACKLOG'!$L:$L,"<>Deferred") -> 15 | N8: =COUNTIF('02_BACKLOG'!$B:$B,$A8) -> 19 | O8: =COUNTIFS('02_BACKLOG'!$B:$B,$A8,'02_BACKLOG'!$L:$L,"Done") -> 0 | P8: =IF(COUNTIFS('02_BACKLOG'!$B:$B,$A8,'02_BACKLOG'!$L:$L,"Deferred")=N8,"Deferred",IF(O8=N8,"Done",IF(COUNTIFS('02_BACKLOG'!$B:$B,$A8,'02_BACKLOG'!$L:$L,"In Progress")+COUNTIFS('02_BACKLOG'!$B:$B,$A8,'02_BACKLOG'!$L:$L,"In Review")>0,"In Progress",IF(COUNTIFS('02_BACKLOG'!$B:$B,$A8,'02_BACKLOG'!$L:$L,"Blocked")>0,"Blocked","Planned")))) -> In Progress
A9: S4 | B9: Weeks 9-10 | C9: ='00_README'!$B$14+(ROW()-5)*'00_README'!$B$15 -> 46328 | D9: =C9+'00_README'!$B$15-1 -> 46341 | E9: Approval, calendar and reliable publishing closed beta | F9: RG-07 / RG-14 / RG-17 | G9: =SUMIFS('02_BACKLOG'!$K:$K,'02_BACKLOG'!$B:$B,$A9,'02_BACKLOG'!$I:$I,"Programmer A") -> 72 | H9: =SUMIFS('02_BACKLOG'!$K:$K,'02_BACKLOG'!$B:$B,$A9,'02_BACKLOG'!$I:$I,"Programmer B") -> 73 | I9: =G9+H9 -> 145 | J9: ='00_README'!$B$16*2 -> 160 | K9: =IFERROR(I9/J9,0) -> 0.90625 | L9: =J9-I9 -> 15 | M9: =COUNTIFS('02_BACKLOG'!$B:$B,$A9,'02_BACKLOG'!$H:$H,"P0",'02_BACKLOG'!$L:$L,"<>Done",'02_BACKLOG'!$L:$L,"<>Deferred") -> 14 | N9: =COUNTIF('02_BACKLOG'!$B:$B,$A9) -> 18 | O9: =COUNTIFS('02_BACKLOG'!$B:$B,$A9,'02_BACKLOG'!$L:$L,"Done") -> 0 | P9: =IF(COUNTIFS('02_BACKLOG'!$B:$B,$A9,'02_BACKLOG'!$L:$L,"Deferred")=N9,"Deferred",IF(O9=N9,"Done",IF(COUNTIFS('02_BACKLOG'!$B:$B,$A9,'02_BACKLOG'!$L:$L,"In Progress")+COUNTIFS('02_BACKLOG'!$B:$B,$A9,'02_BACKLOG'!$L:$L,"In Review")>0,"In Progress",IF(COUNTIFS('02_BACKLOG'!$B:$B,$A9,'02_BACKLOG'!$L:$L,"Blocked")>0,"Blocked","Planned")))) -> In Progress
A10: S5 | B10: Weeks 11-12 | C10: ='00_README'!$B$14+(ROW()-5)*'00_README'!$B$15 -> 46342 | D10: =C10+'00_README'!$B$15-1 -> 46355 | E10: Analytics, billing, entitlements and hardening | F10: RG-08 / RG-11 / RG-12 | G10: =SUMIFS('02_BACKLOG'!$K:$K,'02_BACKLOG'!$B:$B,$A10,'02_BACKLOG'!$I:$I,"Programmer A") -> 73 | H10: =SUMIFS('02_BACKLOG'!$K:$K,'02_BACKLOG'!$B:$B,$A10,'02_BACKLOG'!$I:$I,"Programmer B") -> 69 | I10: =G10+H10 -> 142 | J10: ='00_README'!$B$16*2 -> 160 | K10: =IFERROR(I10/J10,0) -> 0.8875 | L10: =J10-I10 -> 18 | M10: =COUNTIFS('02_BACKLOG'!$B:$B,$A10,'02_BACKLOG'!$H:$H,"P0",'02_BACKLOG'!$L:$L,"<>Done",'02_BACKLOG'!$L:$L,"<>Deferred") -> 10 | N10: =COUNTIF('02_BACKLOG'!$B:$B,$A10) -> 18 | O10: =COUNTIFS('02_BACKLOG'!$B:$B,$A10,'02_BACKLOG'!$L:$L,"Done") -> 0 | P10: =IF(COUNTIFS('02_BACKLOG'!$B:$B,$A10,'02_BACKLOG'!$L:$L,"Deferred")=N10,"Deferred",IF(O10=N10,"Done",IF(COUNTIFS('02_BACKLOG'!$B:$B,$A10,'02_BACKLOG'!$L:$L,"In Progress")+COUNTIFS('02_BACKLOG'!$B:$B,$A10,'02_BACKLOG'!$L:$L,"In Review")>0,"In Progress",IF(COUNTIFS('02_BACKLOG'!$B:$B,$A10,'02_BACKLOG'!$L:$L,"Blocked")>0,"Blocked","Planned")))) -> In Progress
A11: S6 | B11: Weeks 13-14 | C11: ='00_README'!$B$14+(ROW()-5)*'00_README'!$B$15 -> 46356 | D11: =C11+'00_README'!$B$15-1 -> 46369 | E11: Marketing OS: strategy, campaigns, HQ, copilot, safety/cost foundation | F11: RG-15 / RG-16 / RG-17 / RG-18 | G11: =SUMIFS('02_BACKLOG'!$K:$K,'02_BACKLOG'!$B:$B,$A11,'02_BACKLOG'!$I:$I,"Programmer A") -> 81 | H11: =SUMIFS('02_BACKLOG'!$K:$K,'02_BACKLOG'!$B:$B,$A11,'02_BACKLOG'!$I:$I,"Programmer B") -> 71 | I11: =G11+H11 -> 152 | J11: ='00_README'!$B$16*2 -> 160 | K11: =IFERROR(I11/J11,0) -> 0.95 | L11: =J11-I11 -> 8 | M11: =COUNTIFS('02_BACKLOG'!$B:$B,$A11,'02_BACKLOG'!$H:$H,"P0",'02_BACKLOG'!$L:$L,"<>Done",'02_BACKLOG'!$L:$L,"<>Deferred") -> 10 | N11: =COUNTIF('02_BACKLOG'!$B:$B,$A11) -> 20 | O11: =COUNTIFS('02_BACKLOG'!$B:$B,$A11,'02_BACKLOG'!$L:$L,"Done") -> 0 | P11: =IF(COUNTIFS('02_BACKLOG'!$B:$B,$A11,'02_BACKLOG'!$L:$L,"Deferred")=N11,"Deferred",IF(O11=N11,"Done",IF(COUNTIFS('02_BACKLOG'!$B:$B,$A11,'02_BACKLOG'!$L:$L,"In Progress")+COUNTIFS('02_BACKLOG'!$B:$B,$A11,'02_BACKLOG'!$L:$L,"In Review")>0,"In Progress",IF(COUNTIFS('02_BACKLOG'!$B:$B,$A11,'02_BACKLOG'!$L:$L,"Blocked")>0,"Blocked","Planned")))) -> In Progress
A12: S7 | B12: Weeks 15-16 | C12: ='00_README'!$B$14+(ROW()-5)*'00_README'!$B$15 -> 46370 | D12: =C12+'00_README'!$B$15-1 -> 46383 | E12: GA feature completeness: learning, safety, admin, billing edge cases, UX reliability | F12: RG-08 / RG-15 / RG-16 / RG-17 / RG-18 | G12: =SUMIFS('02_BACKLOG'!$K:$K,'02_BACKLOG'!$B:$B,$A12,'02_BACKLOG'!$I:$I,"Programmer A") -> 83 | H12: =SUMIFS('02_BACKLOG'!$K:$K,'02_BACKLOG'!$B:$B,$A12,'02_BACKLOG'!$I:$I,"Programmer B") -> 70 | I12: =G12+H12 -> 153 | J12: ='00_README'!$B$16*2 -> 160 | K12: =IFERROR(I12/J12,0) -> 0.95625 | L12: =J12-I12 -> 7 | M12: =COUNTIFS('02_BACKLOG'!$B:$B,$A12,'02_BACKLOG'!$H:$H,"P0",'02_BACKLOG'!$L:$L,"<>Done",'02_BACKLOG'!$L:$L,"<>Deferred") -> 13 | N12: =COUNTIF('02_BACKLOG'!$B:$B,$A12) -> 20 | O12: =COUNTIFS('02_BACKLOG'!$B:$B,$A12,'02_BACKLOG'!$L:$L,"Done") -> 0 | P12: =IF(COUNTIFS('02_BACKLOG'!$B:$B,$A12,'02_BACKLOG'!$L:$L,"Deferred")=N12,"Deferred",IF(O12=N12,"Done",IF(COUNTIFS('02_BACKLOG'!$B:$B,$A12,'02_BACKLOG'!$L:$L,"In Progress")+COUNTIFS('02_BACKLOG'!$B:$B,$A12,'02_BACKLOG'!$L:$L,"In Review")>0,"In Progress",IF(COUNTIFS('02_BACKLOG'!$B:$B,$A12,'02_BACKLOG'!$L:$L,"Blocked")>0,"Blocked","Planned")))) -> In Progress
A13: S8 | B13: Weeks 17-18 | C13: ='00_README'!$B$14+(ROW()-5)*'00_README'!$B$15 -> 46384 | D13: =C13+'00_README'!$B$15-1 -> 46397 | E13: Production GA hardening, UAT, DR, Meta readiness and progressive launch | F13: RG-04 / RG-09 / RG-12 / RG-13 / RG-14 / RG-17 / RG-18 | G13: =SUMIFS('02_BACKLOG'!$K:$K,'02_BACKLOG'!$B:$B,$A13,'02_BACKLOG'!$I:$I,"Programmer A") -> 50 | H13: =SUMIFS('02_BACKLOG'!$K:$K,'02_BACKLOG'!$B:$B,$A13,'02_BACKLOG'!$I:$I,"Programmer B") -> 66 | I13: =G13+H13 -> 116 | J13: ='00_README'!$B$16*2 -> 160 | K13: =IFERROR(I13/J13,0) -> 0.725 | L13: =J13-I13 -> 44 | M13: =COUNTIFS('02_BACKLOG'!$B:$B,$A13,'02_BACKLOG'!$H:$H,"P0",'02_BACKLOG'!$L:$L,"<>Done",'02_BACKLOG'!$L:$L,"<>Deferred") -> 14 | N13: =COUNTIF('02_BACKLOG'!$B:$B,$A13) -> 16 | O13: =COUNTIFS('02_BACKLOG'!$B:$B,$A13,'02_BACKLOG'!$L:$L,"Done") -> 0 | P13: =IF(COUNTIFS('02_BACKLOG'!$B:$B,$A13,'02_BACKLOG'!$L:$L,"Deferred")=N13,"Deferred",IF(O13=N13,"Done",IF(COUNTIFS('02_BACKLOG'!$B:$B,$A13,'02_BACKLOG'!$L:$L,"In Progress")+COUNTIFS('02_BACKLOG'!$B:$B,$A13,'02_BACKLOG'!$L:$L,"In Review")>0,"In Progress",IF(COUNTIFS('02_BACKLOG'!$B:$B,$A13,'02_BACKLOG'!$L:$L,"Blocked")>0,"Blocked","Planned")))) -> In Progress
A14: S9 | B14: Weeks 19-20 | C14: ='00_README'!$B$14+(ROW()-5)*'00_README'!$B$15 -> 46398 | D14: =C14+'00_README'!$B$15-1 -> 46411 | E14: Growth formats and agency productivity | F14: RG-19 | G14: =SUMIFS('02_BACKLOG'!$K:$K,'02_BACKLOG'!$B:$B,$A14,'02_BACKLOG'!$I:$I,"Programmer A") -> 41 | H14: =SUMIFS('02_BACKLOG'!$K:$K,'02_BACKLOG'!$B:$B,$A14,'02_BACKLOG'!$I:$I,"Programmer B") -> 44 | I14: =G14+H14 -> 85 | J14: ='00_README'!$B$16*2 -> 160 | K14: =IFERROR(I14/J14,0) -> 0.53125 | L14: =J14-I14 -> 75 | M14: =COUNTIFS('02_BACKLOG'!$B:$B,$A14,'02_BACKLOG'!$H:$H,"P0",'02_BACKLOG'!$L:$L,"<>Done",'02_BACKLOG'!$L:$L,"<>Deferred") -> 0 | N14: =COUNTIF('02_BACKLOG'!$B:$B,$A14) -> 10 | O14: =COUNTIFS('02_BACKLOG'!$B:$B,$A14,'02_BACKLOG'!$L:$L,"Done") -> 0 | P14: =IF(COUNTIFS('02_BACKLOG'!$B:$B,$A14,'02_BACKLOG'!$L:$L,"Deferred")=N14,"Deferred",IF(O14=N14,"Done",IF(COUNTIFS('02_BACKLOG'!$B:$B,$A14,'02_BACKLOG'!$L:$L,"In Progress")+COUNTIFS('02_BACKLOG'!$B:$B,$A14,'02_BACKLOG'!$L:$L,"In Review")>0,"In Progress",IF(COUNTIFS('02_BACKLOG'!$B:$B,$A14,'02_BACKLOG'!$L:$L,"Blocked")>0,"Blocked","Planned")))) -> Deferred
A15: S10 | B15: Weeks 21-22 | C15: ='00_README'!$B$14+(ROW()-5)*'00_README'!$B$15 -> 46412 | D15: =C15+'00_README'!$B$15-1 -> 46425 | E15: Growth automation, reporting, multilingual and experiments | F15: Post-GA | G15: =SUMIFS('02_BACKLOG'!$K:$K,'02_BACKLOG'!$B:$B,$A15,'02_BACKLOG'!$I:$I,"Programmer A") -> 38 | H15: =SUMIFS('02_BACKLOG'!$K:$K,'02_BACKLOG'!$B:$B,$A15,'02_BACKLOG'!$I:$I,"Programmer B") -> 38 | I15: =G15+H15 -> 76 | J15: ='00_README'!$B$16*2 -> 160 | K15: =IFERROR(I15/J15,0) -> 0.475 | L15: =J15-I15 -> 84 | M15: =COUNTIFS('02_BACKLOG'!$B:$B,$A15,'02_BACKLOG'!$H:$H,"P0",'02_BACKLOG'!$L:$L,"<>Done",'02_BACKLOG'!$L:$L,"<>Deferred") -> 0 | N15: =COUNTIF('02_BACKLOG'!$B:$B,$A15) -> 10 | O15: =COUNTIFS('02_BACKLOG'!$B:$B,$A15,'02_BACKLOG'!$L:$L,"Done") -> 0 | P15: =IF(COUNTIFS('02_BACKLOG'!$B:$B,$A15,'02_BACKLOG'!$L:$L,"Deferred")=N15,"Deferred",IF(O15=N15,"Done",IF(COUNTIFS('02_BACKLOG'!$B:$B,$A15,'02_BACKLOG'!$L:$L,"In Progress")+COUNTIFS('02_BACKLOG'!$B:$B,$A15,'02_BACKLOG'!$L:$L,"In Review")>0,"In Progress",IF(COUNTIFS('02_BACKLOG'!$B:$B,$A15,'02_BACKLOG'!$L:$L,"Blocked")>0,"Blocked","Planned")))) -> Deferred
A17: TOTAL | G17: =SUM(G5:G15) -> 730 | H17: =SUM(H5:H15) -> 719 | I17: =SUM(I5:I15) -> 1449 | J17: =SUM(J5:J15) -> 1760 | K17: =IFERROR(I17/J17,0) -> 0.82329545 | L17: =SUM(L5:L15) -> 311 | M17: =SUM(M5:M15) -> 114 | N17: =SUM(N5:N15) -> 185 | O17: =SUM(O5:O15) -> 0 | P17: Overall plan — gates open

Sheet 02_BACKLOG
A1: Engineering Master Backlog - 185 Exact Tasks
A2: Implementation master: every task has contractual acceptance criteria. S0-S8 = Production GA; S9-S10 = Growth expansion. Filter by Layer, Surface, Scope, Sprint, Owner and Gate.
A4: Task ID | B4: Sprint | C4: Epic | D4: Task | E4: Implementation Detail | F4: Acceptance Criteria | G4: Dependencies | H4: Priority | I4: Owner | J4: Reviewer | K4: Est. Hours | L4: Status | M4: Test Evidence | N4: Release Gate | O4: Security / Data Notes | P4: Deliverable / Artifact | Q4: Planned Start | R4: Planned End | S4: PR / Evidence Link | T4: Layer / Workstream | U4: Product Surface | V4: Release Scope | W4: Nuxt UI / UX Specification | X4: Verification Type | Y4: Vlerësimi i zbatimit | Z4: Çfarë është kryer realisht | AA4: Çfarë mbetet për këtë task | AB4: Prova / kushti për mbyllje | AC4: Provat e kryera dhe kufijtë | AD4: Kodi / gjetjet e auditit | AE4: Gjendja reale e kodit — 2026-09-08 | AF4: Kërkon zhvillim tjetër? | AG4: Kërkon provë / gate? | AH4: Hapi i ardhshëm konkret | AI4: Evidenca e auditit të ri | AJ4: Pronari / reviewer për handoff
A5: S0-A01 | B5: S0 | C5: Architecture | D5: Record ADR-001 modular monolith baseline | E5: Create ADR template and ADR-001 with modules, dependency direction, service-extraction triggers and deployment units. | F5: ADR accepted; no unresolved architecture blocker; repo links ADR from README. | G5: None | H5: P0 | I5: Programmer A | J5: Programmer B | K5: 6 | L5: In Review | M5: Architecture review checklist | N5: RG-01 | O5: Defines trust/service boundaries. | P5: docs/adr/ADR-001.md | Q5: =INDEX('01_ROADMAP'!$C$5:$C$15,MATCH(B5,'01_ROADMAP'!$A$5:$A$15,0)) -> 46272 | R5: =INDEX('01_ROADMAP'!$D$5:$D$15,MATCH(B5,'01_ROADMAP'!$A$5:$A$15,0)) -> 46285 | S5: docs/backlog-partial-progress-2026-09-08.json#S0-A01 | T5: SETUP/PLATFORM | U5: Platform | V5: GA | W5: N/A / API-domain contract consumed by frontend where applicable. | X5: Acceptance Criteria + Test Evidence + Release Gate | Y5: Implementuar — në pranim | Z5: ADR-002 është Accepted dhe dokumenton modular monolith Nuxt/Nitro/PostgreSQL, kufijtë e moduleve, worker-in e ndarë dhe deployment-in. ADR-001 është Superseded; README/status/handoff/validation janë sinkronizuar. Klasifikimi 2026-09-08: ADR dhe lidhjet e dokumentimit janë implementuar; pret architecture review/RG-01. | AA5: Mbeten architecture review checklist, prova e deployment-it të ndarë dhe RG-01. Follow-up-et RLS/runtime-role/observability të ADR-002 nuk janë gates të kaluara. | AB5: Prova e kërkuar nga backlog-u: Architecture review checklist Kriteri për t'u verifikuar (nuk deklarohet i kaluar): ADR accepted; no unresolved architecture blocker; repo links ADR from README. DA-13: Content review në local bypass dhe public verification, pa përshkrime të shërbimeve të paaktivizuara si aktive; operatori pranon versionin publik. Pranimi kërkon edhe gate-et: RG-01. Asnjë gate nuk është shënuar Passed nga ky audit. | AC5: ADR-002 + kontroll statik i dokumenteve; lint dhe TypeScript kaluan. Nuk ka review sign-off të ekipit ose hosted release gate. | AD5: docs/adr/ADR-002-production-modular-monolith.md docs/adr/ADR-001-frontend-demo.md README.md docs/FRONTEND-STATUS.md docs/BACKEND-HANDOFF.md | AE5: Kryer në kod — pret pranim/gate | AF5: Jo për scope-in e rreshtit | AG5: Po | AH5: Mbeten architecture review checklist, prova e deployment-it të ndarë dhe RG-01. Follow-up-et RLS/runtime-role/observability të ADR-002 nuk janë gates të kaluara. | AI5: docs/backlog-code-handoff-2026-09-08.json#S0-A01 | AJ5: Programmer A / review: Programmer B
A6: S0-A02 | B6: S0 | C6: Repository | D6: Bootstrap backend/worker packages | E6: Create FastAPI API and worker packages, src module convention, shared config package and health endpoints. | F6: API/worker start locally; module import rule documented; /health/live returns 200. | G6: S0-A01 | H6: P0 | I6: Programmer A | J6: Programmer B | K6: 8 | L6: In Review | M6: pytest smoke + container smoke | N6: RG-01 | O6: No provider SDK in domain package. | P6: apps/api + apps/worker | Q6: =INDEX('01_ROADMAP'!$C$5:$C$15,MATCH(B6,'01_ROADMAP'!$A$5:$A$15,0)) -> 46272 | R6: =INDEX('01_ROADMAP'!$D$5:$D$15,MATCH(B6,'01_ROADMAP'!$A$5:$A$15,0)) -> 46285 | S6: docs/backlog-partial-progress-2026-09-08.json#S0-A02 | T6: SETUP/PLATFORM | U6: Platform | V6: GA | W6: N/A / API-domain contract consumed by frontend where applicable. | X6: Acceptance Criteria + Test Evidence + Release Gate | Y6: Implementuar — në pranim | Z6: API Nitro dhe publisher funksionojnë nga i njëjti artefakt; /api/health/live dhe /api/health/ready ekzistojnë. Readiness kontrollon DB, migrimin 0013, heartbeat-in kur publishing aktivizohet dhe queue age. Kufijtë e moduleve janë në ADR-002. Klasifikimi 2026-09-08: API dhe worker-i nisen si role të ndara në container; liveness dhe container smoke kalojnë; pret RG-01. | AA6: Duhet container/process smoke me publisher të aktivizuar, deployment i veçantë i worker-it dhe RG-01; Meta App mungon për një start real publishing. | AB6: Prova e kërkuar nga backlog-u: pytest smoke + container smoke Kriteri për t'u verifikuar (nuk deklarohet i kaluar): API/worker start locally; module import rule documented; /health/live returns 200. Pranimi kërkon edhe gate-et: RG-01. Asnjë gate nuk është shënuar Passed nga ky audit. | AC6: Health live/ready kthyen 200 lokalisht; migrimet 0001–0013 u aplikuan. Nuk u krye container smoke. Validimi 2026-09-08: image-i production me Node 24.20.0 u ngrit healthy si web dhe publisher i veçantë; /api/health/live ktheu 200 brenda container-it. | AD6: apps/web/server/api/health/live.get.ts apps/web/server/api/health/ready.get.ts apps/web/server/plugins/publisher.ts docs/adr/ADR-002-production-modular-monolith.md Dockerfile; compose.yaml; apps/web/server/plugins/publisher.ts; apps/web/server/api/health/live.get.ts; docs/DEPLOYMENT.md | AE6: Kryer në kod — pret pranim/gate | AF6: Jo për scope-in e rreshtit | AG6: Po | AH6: Duhet container/process smoke me publisher të aktivizuar, deployment i veçantë i worker-it dhe RG-01; Meta App mungon për një start real publishing. | AI6: docs/backlog-code-handoff-2026-09-08.json#S0-A02 | AJ6: Programmer A / review: Programmer B
A7: S0-A03 | B7: S0 | C7: Backend Tooling | D7: Pin Node.js 24.20.0 and npm 11.19.0 toolchain | E7: Apply ADR-002's Nitro/TypeScript replacement: pin runtime/package manager, enforce the npm lockfile, ESLint/type policy, deterministic Vitest settings, a versioned pre-commit hook and identical local/CI quality commands. | F7: Clean npm ci from lock; exact toolchain check plus lint/type/unit commands reproducible locally, in the Docker clean-room target and CI. | G7: S0-A02 | H7: P0 | I7: Programmer A | J7: Programmer B | K7: 5 | L7: In Review | M7: Clean Node 24.20.0 Docker build: toolchain/lint/type/24 unit/28 integration/build passed | N7: RG-01 | O7: Dependency lock and supply-chain baseline; Docker image pinned by version and digest. | P7: package manifests + package-lock + .npmrc + hooks + docs/TOOLCHAIN.md | Q7: =INDEX('01_ROADMAP'!$C$5:$C$15,MATCH(B7,'01_ROADMAP'!$A$5:$A$15,0)) -> 46272 | R7: =INDEX('01_ROADMAP'!$D$5:$D$15,MATCH(B7,'01_ROADMAP'!$A$5:$A$15,0)) -> 46285 | S7: docs/S0-A03-REPORT-SQ.md | T7: SETUP/PLATFORM | U7: AI Platform | V7: GA | W7: N/A / API-domain contract consumed by frontend where applicable. | X7: Acceptance Criteria + Test Evidence + Release Gate | Y7: Implementuar — në pranim | Z7: ADR-002 maps the unimplemented Python backend to Nitro/TypeScript. Node.js 24.20.0/npm 11.19.0, engine enforcement, npm lockfile, shared quality commands, deterministic Vitest, pre-commit, CI parity and Docker quality gate are implemented. | AA7: Kodi i task-ut nuk ka punë të mbetur. Ekzekuto hosted GitHub Actions; Programmer B konfirmon required check dhe regjistron RG-01 para statusit Done. | AB7: Fresh environment build: clean npm ci; exact toolchain, lint, typecheck, unit/integration and production build; same gate in CI; reviewer/RG-01 sign-off. | AC7: Validimi 2026-09-08: Docker clean-room me Node.js 24.20.0/npm 11.19.0 instaloi 991 paketa nga lockfile; toolchain/lint/typecheck kaluan; 24/24 unit dhe 28/28 PostgreSQL integration tests kaluan; Nuxt/Nitro production build përfundoi. Hosted CI/reviewer sign-off nuk u deklarua lokalisht. | AD7: .nvmrc; .npmrc; package.json; package-lock.json; apps/web/package.json; apps/web/vitest.config.ts; .githooks/pre-commit; scripts/check-toolchain.mjs; scripts/install-git-hooks.mjs; Dockerfile; .github/workflows/frontend.yml; docs/TOOLCHAIN.md; docs/VALIDATION.md; docs/S0-A03-REPORT-SQ.md | AE7: Kryer në kod — pret pranim/gate | AF7: Jo për scope-in e rreshtit | AG7: Po — hosted CI/reviewer | AH7: Ekzekuto hosted GitHub Actions; Programmer B konfirmon required check dhe regjistron RG-01 para statusit Done. | AI7: docs/S0-A03-REPORT-SQ.md | AJ7: Programmer A / review: Programmer B
A8: S0-A04 | B8: S0 | C8: Database | D8: Bootstrap PostgreSQL environments and migrations | E8: Create local/staging/prod conventions, versioned SQL migrations, separate migration/runtime database roles and a repeatable empty-database strategy. | F8: Local reset succeeds from zero; migration/runtime roles are separated; staging dry-run documented; no production credentials committed. | G8: S0-A01 | H8: P0 | I8: Programmer A | J8: Programmer B | K8: 8 | L8: In Review | M8: PostgreSQL empty-database reset + migration/runtime role smoke | N8: RG-01 | O8: Environment isolation; secret handling. | P8: Docker/ migrations + role provisioning + deploy runbook | Q8: =INDEX('01_ROADMAP'!$C$5:$C$15,MATCH(B8,'01_ROADMAP'!$A$5:$A$15,0)) -> 46272 | R8: =INDEX('01_ROADMAP'!$D$5:$D$15,MATCH(B8,'01_ROADMAP'!$A$5:$A$15,0)) -> 46285 | S8: docs/backlog-deep-audit-2026-09-07.json#S0-A04 | T8: DATABASE | U8: Platform | V8: GA | W8: N/A / API-domain contract consumed by frontend where applicable. | X8: Acceptance Criteria + Test Evidence + Release Gate | Y8: Implementuar — në pranim | Z8: PostgreSQL në Docker, migrime SQL me checksum/transaksion/advisory lock, target i veçantë migrimi dhe rol runtime pa DDL. Klasifikimi 2026-09-08: PostgreSQL reset/migrimet dhe rolet migration/runtime janë implementuar e provuar; pret staging/RG-01. | AA8: Ekzekuto migration dry-run në staging me role të ndara dhe regjistro RG-01; kjo kërkon mjedisin e hostuar. | AB8: Prova e kërkuar: empty-database migration smoke, runtime DDL-deny, staging dry-run dhe RG-01. | AC8: hq-deep-audit-unit.log: schema testuese PostgreSQL nga migrimet, JPEG decode/EXIF, ownership checks, token encryption/transport dhe signed media. Nuk është RLS/ASVS/Meta OAuth acceptance e plotë. Validimi 2026-09-08: target-i migrations aplikoi migrimet 0001–0013 mbi databazën e përkohshme rrit_migration_smoke nga zero dhe u verifikuan 13 rreshta në schema_migrations. Staging dry-run mbetet. Validimi 2026-09-08: target-i migrations aplikoi migrimet 0001–0013 mbi databazën e përkohshme rrit_migration_smoke nga zero dhe u verifikuan 13 rreshta në schema_migrations. Roli runtime lexoi skemën dhe kaloi 8/8 E2E, ndërsa CREATE TABLE u refuzua me permission denied. Staging dry-run mbetet. Validimi 2026-09-08: target-i migrations aplikoi migrimet 0001–0015 dhe migrimet u provuan nga zero në skemën e izoluar të integration suite. Roli runtime lexoi skemën dhe kaloi 8/8 E2E, ndërsa CREATE TABLE u refuzua me permission denied. Staging dry-run mbetet. Validimi 2026-09-08: target-i migrations aplikoi migrimet 0001–0017 dhe migrimet u provuan nga zero në skemën e izoluar të integration suite. Roli runtime lexoi skemën dhe kaloi 8/8 E2E, ndërsa CREATE TABLE u refuzua me permission denied. Staging dry-run mbetet. | AD8: compose.yaml apps/web/scripts/migrate.mjs apps/web/database/migrations apps/web/tests/integration/server.test.ts Dockerfile; compose.yaml; apps/web/scripts/migrate.mjs; apps/web/database/migrations; docs/DEPLOYMENT.md Dockerfile; compose.yaml; infra/postgres/provision-runtime.sh; scripts/setup-local.mjs; apps/web/scripts/migrate.mjs; apps/web/database/migrations; docs/DEPLOYMENT.md | AE8: Kryer në kod — pret pranim/gate | AF8: Jo për scope-in e rreshtit | AG8: Po | AH8: Ekzekuto migration dry-run në staging me role të ndara dhe regjistro RG-01; kjo kërkon mjedisin e hostuar. | AI8: docs/backlog-code-handoff-2026-09-08.json#S0-A04 | AJ8: Programmer A / review: Programmer B
A9: S0-A05 | B9: S0 | C9: Tenancy | D9: Implement tenant DB context and RLS helpers | E9: Create app_runtime role approach, transaction-scoped app.user_id/app.organization_id context and reusable RLS policy helpers. | F9: Cross-tenant query denied under runtime role; missing tenant context returns no tenant rows/fails safely. | G9: S0-A04 | H9: P0 | I9: Programmer A | J9: Programmer B | K9: 10 | L9: Not Started | M9: SQL integration negative tests | N9: RG-02 | O9: Core tenant isolation boundary. | P9: RLS helper migration/tests | Q9: =INDEX('01_ROADMAP'!$C$5:$C$15,MATCH(B9,'01_ROADMAP'!$A$5:$A$15,0)) -> 46272 | R9: =INDEX('01_ROADMAP'!$D$5:$D$15,MATCH(B9,'01_ROADMAP'!$A$5:$A$15,0)) -> 46285 | S9: docs/backlog-deep-audit-2026-09-07.json#S0-A05 | T9: FRONTEND | U9: Platform | V9: GA | W9: N/A / API-domain contract consumed by frontend where applicable. | X9: Acceptance Criteria + Test Evidence + Release Gate | Y9: Pa filluar | Z9: Izolimi aktual bëhet me owner_id/business_id në query-t e aplikacionit. | AA9: 1. Krijo rol runtime pa privilegje të migrimit dhe tenant context për transaksion; aktivizo RLS/policies në çdo tabelë tenant. Provo mungesën e context-it dhe cross-tenant read/write/delete. | AB9: Prova e kërkuar nga backlog-u: SQL integration negative tests Kriteri për t'u verifikuar (nuk deklarohet i kaluar): Cross-tenant query denied under runtime role; missing tenant context returns no tenant rows/fails safely. Pranimi kërkon edhe gate-et: RG-02. Asnjë gate nuk është shënuar Passed nga ky audit. | AC9: U rishikuan kodi/artefaktet dhe u kërkua implementimi i kësaj detyre. Nuk ka provë të ekzekutuar specifike që mbyll të gjithë kriterin; kontrollet globale nuk e zëvendësojnë atë. | AD9: apps/web/server/utils/workspaces.ts apps/web/database/migrations | AE9: Pa filluar | AF9: Po | AG9: Po, pas implementimit | AH9: Krijo rol runtime pa privilegje të migrimit dhe tenant context për transaksion; aktivizo RLS/policies në çdo tabelë tenant. Provo mungesën e context-it dhe cross-tenant read/write/delete. | AI9: docs/backlog-code-handoff-2026-09-08.json#S0-A05 | AJ9: Programmer A / review: Programmer B
A10: S0-A06 | B10: S0 | C10: Tenancy | D10: Build RLS CI test harness | E10: Create fixtures for Org A/B/users and reusable allow/deny assertions; make RLS suite required in CI. | F10: Representative read/write/delete cross-tenant tests fail before policy and pass after; CI blocks regression. | G10: S0-A05 | H10: P0 | I10: Programmer A | J10: Programmer B | K10: 8 | L10: Not Started | M10: pytest DB/RLS suite | N10: RG-02 | O10: Automated isolation verification. | P10: tests/security/rls | Q10: =INDEX('01_ROADMAP'!$C$5:$C$15,MATCH(B10,'01_ROADMAP'!$A$5:$A$15,0)) -> 46272 | R10: =INDEX('01_ROADMAP'!$D$5:$D$15,MATCH(B10,'01_ROADMAP'!$A$5:$A$15,0)) -> 46285 | S10: docs/backlog-deep-audit-2026-09-07.json#S0-A06 | T10: DATABASE | U10: Platform | V10: GA | W10: N/A / API-domain contract consumed by frontend where applicable. | X10: Acceptance Criteria + Test Evidence + Release Gate | Y10: Pa filluar | Z10: Izolimi aktual bëhet me owner_id/business_id në query-t e aplikacionit. | AA10: 1. Ndërto fixture Org A/B dhe helper allow/deny nën rolin runtime; lidhe suite RLS me required CI. Hiq një policy qëllimisht dhe provo se CI dështon. | AB10: Prova e kërkuar nga backlog-u: pytest DB/RLS suite Kriteri për t'u verifikuar (nuk deklarohet i kaluar): Representative read/write/delete cross-tenant tests fail before policy and pass after; CI blocks regression. Pranimi kërkon edhe gate-et: RG-02. Asnjë gate nuk është shënuar Passed nga ky audit. | AC10: U rishikuan kodi/artefaktet dhe u kërkua implementimi i kësaj detyre. Nuk ka provë të ekzekutuar specifike që mbyll të gjithë kriterin; kontrollet globale nuk e zëvendësojnë atë. | AD10: apps/web/server/utils/workspaces.ts apps/web/database/migrations | AE10: Pa filluar | AF10: Po | AG10: Po, pas implementimit | AH10: Ndërto fixture Org A/B dhe helper allow/deny nën rolin runtime; lidhe suite RLS me required CI. Hiq një policy qëllimisht dhe provo se CI dështon. | AI10: docs/backlog-code-handoff-2026-09-08.json#S0-A06 | AJ10: Programmer A / review: Programmer B
A11: S0-A07 | B11: S0 | C11: Authentication | D11: Verify Better Auth sessions in Nitro | E11: Validate opaque database sessions through Better Auth on every protected Nitro endpoint; enforce expiry, revocation, forged-cookie rejection and exact-origin checks for mutations. | F11: Valid session accepted; expired, revoked and forged session rejected with AUTH_REQUIRED; untrusted mutation origin rejected with ORIGIN_REJECTED. | G11: S0-A02,S0-A04 | H11: P0 | I11: Programmer A | J11: Programmer B | K11: 8 | L11: In Review | M11: Production-container auth session E2E | N11: RG-03 | O11: No token body logged. | P11: Central session/origin guard + auth acceptance suite | Q11: =INDEX('01_ROADMAP'!$C$5:$C$15,MATCH(B11,'01_ROADMAP'!$A$5:$A$15,0)) -> 46272 | R11: =INDEX('01_ROADMAP'!$D$5:$D$15,MATCH(B11,'01_ROADMAP'!$A$5:$A$15,0)) -> 46285 | S11: docs/backlog-deep-audit-2026-09-07.json#S0-A07 | T11: SECURITY | U11: Auth | V11: GA | W11: N/A / API-domain contract consumed by frontend where applicable. | X11: Acceptance Criteria + Test Evidence + Release Gate | Y11: Implementuar — në pranim | Z11: Better Auth me sessione opaque në PostgreSQL, cookie cache të çaktivizuar, skadim 7-ditor, revokim pas logout/reset dhe guard i përbashkët për API-të. Klasifikimi 2026-09-08: Better Auth session guard pranon sesionin valid dhe refuzon forged/revoked/expired me kode stabile; pret RG-03. | AA11: Ekzekuto suite-n në hosted CI/public staging dhe regjistro security review/RG-03. | AB11: Prova e kërkuar: valid/forged/revoked/expired session E2E, origin rejection dhe RG-03. | AC11: U rishikuan kodi/artefaktet dhe u kërkua implementimi i kësaj detyre. Nuk ka provë të ekzekutuar specifike që mbyll të gjithë kriterin; kontrollet globale nuk e zëvendësojnë atë. Validimi 2026-09-08: E2E mbi container-in production provoi sesion valid, cookie të falsifikuar, logout/revokim dhe expiresAt të kaluar; përgjigjja e mbrojtur ktheu AUTH_REQUIRED. Origin-i i huaj u refuzua me ORIGIN_REJECTED. | AD11: apps/web/server/utils/auth.ts apps/web/server/utils/access.ts apps/web/tests/e2e/local-registration.spec.ts apps/web/server/utils/auth.ts; apps/web/server/utils/access.ts; apps/web/server/utils/auth-configuration.ts; apps/web/tests/e2e/auth-session.spec.ts; apps/web/tests/e2e/local-registration.spec.ts | AE11: Kryer në kod — pret pranim/gate | AF11: Jo për scope-in e rreshtit | AG11: Po | AH11: Ekzekuto suite-n në hosted CI/public staging dhe regjistro security review/RG-03. | AI11: docs/backlog-code-handoff-2026-09-08.json#S0-A07 | AJ11: Programmer A / review: Programmer B
A12: S0-A08 | B12: S0 | C12: Async Platform | D12: Create durable queue/outbox skeleton | E12: Enable Supabase Queues/pgmq locally, define JobEnvelope, outbox table and generic idempotent consumer base. | F12: Test event commits with outbox; dispatcher enqueues; worker consumes once logically under duplicate delivery. | G12: S0-A04 | H12: P0 | I12: Programmer A | J12: Programmer B | K12: 10 | L12: In Review | M12: queue duplicate/crash tests | N12: RG-01 | O12: Queue not exposed to browser. | P12: queue/outbox framework | Q12: =INDEX('01_ROADMAP'!$C$5:$C$15,MATCH(B12,'01_ROADMAP'!$A$5:$A$15,0)) -> 46272 | R12: =INDEX('01_ROADMAP'!$D$5:$D$15,MATCH(B12,'01_ROADMAP'!$A$5:$A$15,0)) -> 46285 | S12: docs/backlog-deep-audit-2026-09-07.json#S0-A08 | T12: SETUP/PLATFORM | U12: Platform | V12: GA | W12: N/A / API-domain contract consumed by frontend where applicable. | X12: Acceptance Criteria + Test Evidence + Release Gate | Y12: Implementuar — në pranim | Z12: Outbox PostgreSQL me envelope/version/dedupe, claim FOR UPDATE SKIP LOCKED, lease recovery, receipt të konsumit dhe transaksion të njëjtë për efektet DB. Klasifikimi 2026-09-08: Outbox-i transaksional, claim me lease/SKIP LOCKED, deduplication dhe crash recovery janë implementuar; pret RG-01. | AA12: Ekzekuto hosted CI/container failure rehearsal dhe regjistro RG-01; adapterët me side-effect të jashtëm vazhdojnë të përdorin idempotency/reconciliation specifik. | AB12: Prova e kërkuar: queue duplicate/crash/concurrency tests, container smoke dhe RG-01. | AC12: U rishikuan kodi/artefaktet dhe u kërkua implementimi i kësaj detyre. Nuk ka provë të ekzekutuar specifike që mbyll të gjithë kriterin; kontrollet globale nuk e zëvendësojnë atë. Validimi 2026-09-08: migrimi 0014 krijoi JobEnvelope/outbox receipts; testet provuan commit/rollback atomik, dedupe, dy consumer-a paralelë me vetëm një efekt dhe rikuperim të claim-it stale. Readiness production kërkon migrimin 0014. Validimi 2026-09-08: migrimi 0014 krijoi JobEnvelope/outbox receipts; testet provuan commit/rollback atomik, dedupe, dy consumer-a paralelë me vetëm një efekt dhe rikuperim të claim-it stale. Readiness production kërkon migrimin minimal aktual 0015. Validimi 2026-09-08: migrimi 0014 krijoi JobEnvelope/outbox receipts; testet provuan commit/rollback atomik, dedupe, dy consumer-a paralelë me vetëm një efekt dhe rikuperim të claim-it stale. Readiness production kërkon migrimin minimal aktual 0017. | AD12: apps/web/database/migrations/0004_trials_and_social.sql apps/web/server/utils/publishing.ts apps/web/database/migrations/0014_durable_outbox.sql; apps/web/server/utils/outbox.ts; apps/web/tests/integration/server.test.ts; apps/web/server/api/health/ready.get.ts | AE12: Kryer në kod — pret pranim/gate | AF12: Jo për scope-in e rreshtit | AG12: Po | AH12: Ekzekuto hosted CI/container failure rehearsal dhe regjistro RG-01; adapterët me side-effect të jashtëm vazhdojnë të përdorin idempotency/reconciliation specifik. | AI12: docs/backlog-code-handoff-2026-09-08.json#S0-A08 | AJ12: Programmer A / review: Programmer B
A13: S0-A09 | B13: S0 | C13: CI/CD | D13: Create backend/security CI gates | E13: Add lint, types, unit, DB reset/RLS, secret scan, dependency scan and container build jobs with caching. | F13: PR cannot merge when any gate fails; CI artifacts include test reports. | G13: S0-A03,S0-A04,S0-A06 | H13: P0 | I13: Programmer A | J13: Programmer B | K13: 8 | L13: In Progress | M13: Deliberate failing PR checks | N13: RG-01 | O13: Secure SDLC baseline. | P13: .github/workflows backend | Q13: =INDEX('01_ROADMAP'!$C$5:$C$15,MATCH(B13,'01_ROADMAP'!$A$5:$A$15,0)) -> 46272 | R13: =INDEX('01_ROADMAP'!$D$5:$D$15,MATCH(B13,'01_ROADMAP'!$A$5:$A$15,0)) -> 46285 | S13: docs/backlog-partial-progress-2026-09-08.json#S0-A09 | T13: SECURITY | U13: Security | V13: GA | W13: N/A / API-domain contract consumed by frontend where applicable. | X13: Acceptance Criteria + Test Evidence + Release Gate | Y13: Pjesërisht | Z13: CI provisionon PostgreSQL, env vetëm testues, aplikon migrimet, ndërton output-in, pret readiness, ekzekuton lint/type/unit/E2E/audit dhe ngarkon artefakte. | AA13: Mbeten run hosted, required branch checks, deliberate failing PR dhe gates RLS/secret/container. Workspace nuk ka .git, prandaj merge blocking nuk mund të provohet lokalisht. | AB13: Prova e kërkuar nga backlog-u: Deliberate failing PR checks Kriteri për t'u verifikuar (nuk deklarohet i kaluar): PR cannot merge when any gate fails; CI artifacts include test reports. DA-08: CI nga checkout i pastër kalon testet me DB; heqja e një guard-i e bllokon merge-in. Arkivo raportet pa sekrete. Pranimi kërkon edhe gate-et: RG-01. Asnjë gate nuk është shënuar Passed nga ky audit. | AC13: Workflow u validua nga lint/lexim dhe konfigurimi lokal ekuivalent kaloi; hosted GitHub Actions nuk u ekzekutua. Validimi 2026-09-08: workflow-i kaloi actionlint dhe tani ndërton/nis image-in e ngurtësuar për E2E; required-check/merge-blocking në GitHub mbetet provë e jashtme. | AD13: .github/workflows/frontend.yml apps/web/server/api/health/ready.get.ts .nvmrc .github/workflows/frontend.yml; Dockerfile; docs/VALIDATION.md | AE13: Pjesërisht — kërkon zhvillim | AF13: Po | AG13: Po, pas implementimit | AH13: Mbeten run hosted, required branch checks, deliberate failing PR dhe gates RLS/secret/container. Workspace nuk ka .git, prandaj merge blocking nuk mund të provohet lokalisht. | AI13: docs/backlog-code-handoff-2026-09-08.json#S0-A09 | AJ13: Programmer A / review: Programmer B
A14: S0-B01 | B14: S0 | C14: Frontend | D14: Bootstrap Nuxt 4 application | E14: Bootstrap Nuxt 4.5.x on Node.js 24 LTS with strict TypeScript, current Nuxt directory structure, runtime config separation, ESLint/typecheck/test scripts and SSR-ready deployment output. | F14: Clean install/build/typecheck passes from lockfile; Node 24 LTS documented; no secret runtime config exposed client-side. | G14: S0-A01 | H14: P0 | I14: Programmer B | J14: Programmer A | K14: 8 | L14: In Review | M14: nuxt build + typecheck | N14: RG-01 | O14: Public/private config separated. | P14: apps/web | Q14: =INDEX('01_ROADMAP'!$C$5:$C$15,MATCH(B14,'01_ROADMAP'!$A$5:$A$15,0)) -> 46272 | R14: =INDEX('01_ROADMAP'!$D$5:$D$15,MATCH(B14,'01_ROADMAP'!$A$5:$A$15,0)) -> 46285 | S14: docs/backlog-partial-progress-2026-09-08.json#S0-B01 | T14: FRONTEND | U14: Platform | V14: GA | W14: See companion DOCX; use Nuxt UI primitives and shared design system for user-facing tasks. | X14: Acceptance Criteria + Test Evidence + Release Gate | Y14: Implementuar — në pranim | Z14: Nuxt 4.5.2/Nuxt UI 4.11.0 me TypeScript strict; .nvmrc tani fikson Node 24. Lint dhe app/server typecheck kalojnë dhe sekretet mbeten server-side. Klasifikimi 2026-09-08: Nuxt/TypeScript/runtime separation është implementuar; pret clean Node 24 build/RG-01. | AA14: Duhet npm ci + production build nga checkout i pastër me Node 24 dhe RG-01. Makina e këtij auditimi po përdor Node 26.5.0. | AB14: Prova e kërkuar nga backlog-u: nuxt build + typecheck Kriteri për t'u verifikuar (nuk deklarohet i kaluar): Clean install/build/typecheck passes from lockfile; Node 24 LTS documented; no secret runtime config exposed client-side. Pranimi kërkon edhe gate-et: RG-01. Asnjë gate nuk është shënuar Passed nga ky audit. | AC14: ESLint exit 0; vue-tsc app exit 0; tsc server exit 0. Clean Node 24 build nuk u ekzekutua. Validimi 2026-09-08: clean npm ci, nuxt typecheck dhe production build kaluan brenda image-it Node 24.20.0 të fiksuar me digest. | AD14: .nvmrc apps/web/package.json apps/web/nuxt.config.ts hq-partials-lint-2.log Dockerfile; .nvmrc; package-lock.json; apps/web/package.json; docs/VALIDATION.md | AE14: Kryer në kod — pret pranim/gate | AF14: Jo për scope-in e rreshtit | AG14: Po | AH14: Duhet npm ci + production build nga checkout i pastër me Node 24 dhe RG-01. Makina e këtij auditimi po përdor Node 26.5.0. | AI14: docs/backlog-code-handoff-2026-09-08.json#S0-B01 | AJ14: Programmer B / review: Programmer A
A15: S0-B02 | B15: S0 | C15: Design System | D15: Create visual tokens and base components | E15: Adopt Nuxt UI v4 as primary component system. Define app.config theme, semantic color/type/spacing/radius/elevation/motion tokens, light/dark variants, icon policy and branded wrappers only where needed. | F15: Tokens drive landing and dashboard; no random feature-level design constants; contrast baseline passes; dark mode has no unreadable states. | G15: S0-B01 | H15: P1 | I15: Programmer B | J15: Programmer A | K15: 9 | L15: In Review | M15: Vitest/component visual QA | N15: RG-14 | O15: Accessible primitives reduce later regressions. | P15: packages/design or web components | Q15: =INDEX('01_ROADMAP'!$C$5:$C$15,MATCH(B15,'01_ROADMAP'!$A$5:$A$15,0)) -> 46272 | R15: =INDEX('01_ROADMAP'!$D$5:$D$15,MATCH(B15,'01_ROADMAP'!$A$5:$A$15,0)) -> 46285 | S15: docs/S0-B02-REPORT-SQ.md | T15: FRONTEND | U15: Platform | V15: GA | W15: See companion DOCX; use Nuxt UI primitives and shared design system for user-facing tasks. | X15: Acceptance Criteria + Test Evidence + Release Gate | Y15: Në review | Z15: U vendos kontrata e përbashkët `--rrit-*` për ngjyra semantike, tipografi, hapësirë, radius, hije dhe motion. Landing dhe dashboard konsumojnë tokenat e UI-së; Nuxt UI v4, Lucide dhe politika e wrapper-ave janë të dokumentuara. Light/dark tokenat dhe testet accessibility u shtuan. | AA15: Mbeten GitHub Actions në PR, review i Programmer A dhe RG-14. Testi i dashboard accessibility krijon të dhëna sintetike dhe duhet të ekzekutohet vetëm në ambient të dedikuar/CI, jo kundër Supabase v1. | AB15: Kriteri lokal i verifikuar: tokenat përdoren për UI standarde në landing dhe dashboard; light/dark accessibility baseline kalon për landing. Ilustrimet e landing-ut lejohen të mbajnë ngjyra/gradientë lokalë sepse janë art-direction, jo konstante të UI-së. RG-14 nuk është shënuar Passed. | AC15: 2026-09-09: `npm.cmd run check` kaloi (toolchain, ESLint, Nuxt typecheck, 27/27 Vitest unit); `npm.cmd run build` kaloi; Playwright landing desktop kaloi 13/13 me kontroll light/dark. `git diff --check` kaloi. | AD15: apps/web/app/assets/css/main.css apps/web/app/assets/css/landing.css apps/web/app/utils/design-system.ts apps/web/app/app.config.ts apps/web/tests/unit/design-system.test.ts apps/web/tests/e2e/accessibility-baseline.spec.ts docs/S0-B02-REPORT-SQ.md | AE15: Në review — implementimi dhe validimi lokal u kryen; CI/review/RG-14 mbeten. | AF15: Po | AG15: Po, pas implementimit | AH15: Ka ende konstante stili në komponentë; duhet rishikim kontrasti/dark mode dhe provë vizuale e versionit aktual. | AI15: docs/backlog-code-handoff-2026-09-08.json#S0-B02 | AJ15: Programmer B / review: Programmer A
A16: S0-B03 | B16: S0 | C16: Frontend | D16: Build authenticated application shell | E16: Build dashboard shell using Nuxt UI DashboardGroup/DashboardSidebar/DashboardNavbar/DashboardToolbar/DashboardSearch with persistent collapse state, org/brand switcher slots and mobile navigation. | F16: Desktop/tablet/mobile shell is keyboard accessible; navigation persists correctly; active org/brand context visible; no layout shift blocker. | G16: S0-B01,S0-B02 | H16: P0 | I16: Programmer B | J16: Programmer A | K16: 8 | L16: In Review | M16: component + Playwright shell smoke | N16: RG-14 | O16: No auth decisions trusted only to UI. | P16: app layout | Q16: =INDEX('01_ROADMAP'!$C$5:$C$15,MATCH(B16,'01_ROADMAP'!$A$5:$A$15,0)) -> 46272 | R16: =INDEX('01_ROADMAP'!$D$5:$D$15,MATCH(B16,'01_ROADMAP'!$A$5:$A$15,0)) -> 46285 | S16: docs/backlog-deep-audit-2026-09-07.json#S0-B03 | T16: FRONTEND | U16: Auth | V16: GA | W16: See companion DOCX; use Nuxt UI primitives and shared design system for user-facing tasks. | X16: Acceptance Criteria + Test Evidence + Release Gate | Y16: Implementuar — në pranim | Z16: Shell me USidebar/UDashboardPanel, navigim, kërkim, kontekst biznesi real, collapse dhe pamje mobile. | AA16: 1. Për scope-in me një biznes për pronar, kodi është implementuar. Mbeten pranim i plotë keyboard/tablet/a11y dhe RG-14; multi-org switcher është jashtë rrjedhës aktuale. | AB16: Prova e kërkuar nga backlog-u: component + Playwright shell smoke Kriteri për t'u verifikuar (nuk deklarohet i kaluar): Desktop/tablet/mobile shell is keyboard accessible; navigation persists correctly; active org/brand context visible; no layout shift blocker. Pranimi kërkon edhe gate-et: RG-14. Asnjë gate nuk është shënuar Passed nga ky audit. | AC16: hq-deep-audit-live-e2e-rerun.log: 4/4. Business/media/validation/revision conflict dhe pagination 13 postime; axe dhe overflow në overview/content/gallery/calendar/social-posts/billing/settings-security, 1440px/390px Chromium. Nuk është Firefox/WebKit/real-device/fault/UAT matrix. | AD16: apps/web/app/layouts/dashboard.vue apps/web/app/components/DashboardPage.vue hq-optional-e2e.log | AE16: Kryer në kod — pret pranim/gate | AF16: Jo për scope-in e rreshtit | AG16: Po | AH16: Për scope-in me një biznes për pronar, kodi është implementuar. Mbeten pranim i plotë keyboard/tablet/a11y dhe RG-14; multi-org switcher është jashtë rrjedhës aktuale. | AI16: docs/backlog-code-handoff-2026-09-08.json#S0-B03 | AJ16: Programmer B / review: Programmer A
... A189: S10-B05 | B189: S10 | C189: Recommendation UX | D189: Polish AI next-actions with feedback controls | E189: Show 3-5 ranked actions, reason, expected benefit caveat, do/dismiss/later controls and links to artifact creation. | F189: No endless feed; dismiss works; action state survives refresh; screen reader announces updates. | G189: S10-A05,S6-B10 | H189: P2 | I189: Programmer B | J189: Programmer A | K189: 6 | L189: Deferred | M189: E2E + a11y | N189: Post-GA | O189: Do not overstate predicted performance. | P189: next-action UX | Q189: =INDEX('01_ROADMAP'!$C$5:$C$15,MATCH(B189,'01_ROADMAP'!$A$5:$A$15,0)) -> 46412 | R189: =INDEX('01_ROADMAP'!$D$5:$D$15,MATCH(B189,'01_ROADMAP'!$A$5:$A$15,0)) -> 46425 | S189: docs/backlog-deep-audit-2026-09-07.json#S10-B05 | T189: FRONTEND | U189: Dashboard | V189: Growth | W189: Card/Badge/Dropdown/Toast. | X189: E2E + a11y | Y189: Shtyrë | Z189: Overview ka next-actions të thjeshta nga gjendja; AI ranking/feedback/fatigue suppression mbetet S10. | AA189: 1. Pas ranking API: shfaq 3–5 veprime me arsye/benefit caveat dhe do/dismiss/later; ruaj gjendjen pas refresh, link tek artefakti dhe njoftim screen-reader. | AB189: Prova e kërkuar nga backlog-u: E2E + a11y Kriteri për t'u verifikuar (nuk deklarohet i kaluar): No endless feed; dismiss works; action state survives refresh; screen reader announces updates. Pranimi kërkon edhe gate-et: Post-GA. Asnjë gate nuk është shënuar Passed nga ky audit. | AC189: Shtyrë sipas scope-it; nuk është realizuar. Kriteret dhe hapat e këtij rreshti vlejnë kur moduli të rikthehet në scope. | AD189: Nuk u gjet implementim specifik; shiko kriterin dhe hapat në AA/AB. | AE189: Shtyrë nga scope-i aktual | AF189: Jo në scope-in posts-only | AG189: Jo tani | AH189: Pas ranking API: shfaq 3–5 veprime me arsye/benefit caveat dhe do/dismiss/later; ruaj gjendjen pas refresh, link tek artefakti dhe njoftim screen-reader. | AI189: docs/backlog-code-handoff-2026-09-08.json#S10-B05 | AJ189: Programmer B / review: Programmer A

Sheet 03_WORKLOAD
A1: Developer Workload & Capacity
A2: Utilization is planned task hours / nominal capacity. Remaining capacity is intentional for review, planning, defects, provider work and stabilization.
A4: Sprint | B4: A Hours | C4: A Capacity | D4: A Util. | E4: B Hours | F4: B Capacity | G4: B Util. | H4: Total | I4: Total Capacity | J4: Buffer | K4: Open P0
A5: S0 | B5: =SUMIFS('02_BACKLOG'!$K:$K,'02_BACKLOG'!$B:$B,$A5,'02_BACKLOG'!$I:$I,"Programmer A") -> 71 | C5: ='00_README'!$B$16 -> 80 | D5: =IFERROR(B5/C5,0) -> 0.8875 | E5: =SUMIFS('02_BACKLOG'!$K:$K,'02_BACKLOG'!$B:$B,$A5,'02_BACKLOG'!$I:$I,"Programmer B") -> 71 | F5: ='00_README'!$B$16 -> 80 | G5: =IFERROR(E5/F5,0) -> 0.8875 | H5: =B5+E5 -> 142 | I5: =C5+F5 -> 160 | J5: =I5-H5 -> 18 | K5: =COUNTIFS('02_BACKLOG'!$B:$B,$A5,'02_BACKLOG'!$H:$H,"P0",'02_BACKLOG'!$L:$L,"<>Done",'02_BACKLOG'!$L:$L,"<>Deferred") -> 14
A6: S1 | B6: =SUMIFS('02_BACKLOG'!$K:$K,'02_BACKLOG'!$B:$B,$A6,'02_BACKLOG'!$I:$I,"Programmer A") -> 72 | C6: ='00_README'!$B$16 -> 80 | D6: =IFERROR(B6/C6,0) -> 0.9 | E6: =SUMIFS('02_BACKLOG'!$K:$K,'02_BACKLOG'!$B:$B,$A6,'02_BACKLOG'!$I:$I,"Programmer B") -> 71 | F6: ='00_README'!$B$16 -> 80 | G6: =IFERROR(E6/F6,0) -> 0.8875 | H6: =B6+E6 -> 143 | I6: =C6+F6 -> 160 | J6: =I6-H6 -> 17 | K6: =COUNTIFS('02_BACKLOG'!$B:$B,$A6,'02_BACKLOG'!$H:$H,"P0",'02_BACKLOG'!$L:$L,"<>Done",'02_BACKLOG'!$L:$L,"<>Deferred") -> 9
A7: S2 | B7: =SUMIFS('02_BACKLOG'!$K:$K,'02_BACKLOG'!$B:$B,$A7,'02_BACKLOG'!$I:$I,"Programmer A") -> 75 | C7: ='00_README'!$B$16 -> 80 | D7: =IFERROR(B7/C7,0) -> 0.9375 | E7: =SUMIFS('02_BACKLOG'!$K:$K,'02_BACKLOG'!$B:$B,$A7,'02_BACKLOG'!$I:$I,"Programmer B") -> 70 | F7: ='00_README'!$B$16 -> 80 | G7: =IFERROR(E7/F7,0) -> 0.875 | H7: =B7+E7 -> 145 | I7: =C7+F7 -> 160 | J7: =I7-H7 -> 15 | K7: =COUNTIFS('02_BACKLOG'!$B:$B,$A7,'02_BACKLOG'!$H:$H,"P0",'02_BACKLOG'!$L:$L,"<>Done",'02_BACKLOG'!$L:$L,"<>Deferred") -> 15
A8: S3 | B8: =SUMIFS('02_BACKLOG'!$K:$K,'02_BACKLOG'!$B:$B,$A8,'02_BACKLOG'!$I:$I,"Programmer A") -> 74 | C8: ='00_README'!$B$16 -> 80 | D8: =IFERROR(B8/C8,0) -> 0.925 | E8: =SUMIFS('02_BACKLOG'!$K:$K,'02_BACKLOG'!$B:$B,$A8,'02_BACKLOG'!$I:$I,"Programmer B") -> 76 | F8: ='00_README'!$B$16 -> 80 | G8: =IFERROR(E8/F8,0) -> 0.95 | H8: =B8+E8 -> 150 | I8: =C8+F8 -> 160 | J8: =I8-H8 -> 10 | K8: =COUNTIFS('02_BACKLOG'!$B:$B,$A8,'02_BACKLOG'!$H:$H,"P0",'02_BACKLOG'!$L:$L,"<>Done",'02_BACKLOG'!$L:$L,"<>Deferred") -> 15
A9: S4 | B9: =SUMIFS('02_BACKLOG'!$K:$K,'02_BACKLOG'!$B:$B,$A9,'02_BACKLOG'!$I:$I,"Programmer A") -> 72 | C9: ='00_README'!$B$16 -> 80 | D9: =IFERROR(B9/C9,0) -> 0.9 | E9: =SUMIFS('02_BACKLOG'!$K:$K,'02_BACKLOG'!$B:$B,$A9,'02_BACKLOG'!$I:$I,"Programmer B") -> 73 | F9: ='00_README'!$B$16 -> 80 | G9: =IFERROR(E9/F9,0) -> 0.9125 | H9: =B9+E9 -> 145 | I9: =C9+F9 -> 160 | J9: =I9-H9 -> 15 | K9: =COUNTIFS('02_BACKLOG'!$B:$B,$A9,'02_BACKLOG'!$H:$H,"P0",'02_BACKLOG'!$L:$L,"<>Done",'02_BACKLOG'!$L:$L,"<>Deferred") -> 14
A10: S5 | B10: =SUMIFS('02_BACKLOG'!$K:$K,'02_BACKLOG'!$B:$B,$A10,'02_BACKLOG'!$I:$I,"Programmer A") -> 73 | C10: ='00_README'!$B$16 -> 80 | D10: =IFERROR(B10/C10,0) -> 0.9125 | E10: =SUMIFS('02_BACKLOG'!$K:$K,'02_BACKLOG'!$B:$B,$A10,'02_BACKLOG'!$I:$I,"Programmer B") -> 69 | F10: ='00_README'!$B$16 -> 80 | G10: =IFERROR(E10/F10,0) -> 0.8625 | H10: =B10+E10 -> 142 | I10: =C10+F10 -> 160 | J10: =I10-H10 -> 18 | K10: =COUNTIFS('02_BACKLOG'!$B:$B,$A10,'02_BACKLOG'!$H:$H,"P0",'02_BACKLOG'!$L:$L,"<>Done",'02_BACKLOG'!$L:$L,"<>Deferred") -> 10
A11: S6 | B11: =SUMIFS('02_BACKLOG'!$K:$K,'02_BACKLOG'!$B:$B,$A11,'02_BACKLOG'!$I:$I,"Programmer A") -> 81 | C11: ='00_README'!$B$16 -> 80 | D11: =IFERROR(B11/C11,0) -> 1.0125 | E11: =SUMIFS('02_BACKLOG'!$K:$K,'02_BACKLOG'!$B:$B,$A11,'02_BACKLOG'!$I:$I,"Programmer B") -> 71 | F11: ='00_README'!$B$16 -> 80 | G11: =IFERROR(E11/F11,0) -> 0.8875 | H11: =B11+E11 -> 152 | I11: =C11+F11 -> 160 | J11: =I11-H11 -> 8 | K11: =COUNTIFS('02_BACKLOG'!$B:$B,$A11,'02_BACKLOG'!$H:$H,"P0",'02_BACKLOG'!$L:$L,"<>Done",'02_BACKLOG'!$L:$L,"<>Deferred") -> 10
A12: S7 | B12: =SUMIFS('02_BACKLOG'!$K:$K,'02_BACKLOG'!$B:$B,$A12,'02_BACKLOG'!$I:$I,"Programmer A") -> 83 | C12: ='00_README'!$B$16 -> 80 | D12: =IFERROR(B12/C12,0) -> 1.0375 | E12: =SUMIFS('02_BACKLOG'!$K:$K,'02_BACKLOG'!$B:$B,$A12,'02_BACKLOG'!$I:$I,"Programmer B") -> 70 | F12: ='00_README'!$B$16 -> 80 | G12: =IFERROR(E12/F12,0) -> 0.875 | H12: =B12+E12 -> 153 | I12: =C12+F12 -> 160 | J12: =I12-H12 -> 7 | K12: =COUNTIFS('02_BACKLOG'!$B:$B,$A12,'02_BACKLOG'!$H:$H,"P0",'02_BACKLOG'!$L:$L,"<>Done",'02_BACKLOG'!$L:$L,"<>Deferred") -> 13
A13: S8 | B13: =SUMIFS('02_BACKLOG'!$K:$K,'02_BACKLOG'!$B:$B,$A13,'02_BACKLOG'!$I:$I,"Programmer A") -> 50 | C13: ='00_README'!$B$16 -> 80 | D13: =IFERROR(B13/C13,0) -> 0.625 | E13: =SUMIFS('02_BACKLOG'!$K:$K,'02_BACKLOG'!$B:$B,$A13,'02_BACKLOG'!$I:$I,"Programmer B") -> 66 | F13: ='00_README'!$B$16 -> 80 | G13: =IFERROR(E13/F13,0) -> 0.825 | H13: =B13+E13 -> 116 | I13: =C13+F13 -> 160 | J13: =I13-H13 -> 44 | K13: =COUNTIFS('02_BACKLOG'!$B:$B,$A13,'02_BACKLOG'!$H:$H,"P0",'02_BACKLOG'!$L:$L,"<>Done",'02_BACKLOG'!$L:$L,"<>Deferred") -> 14
A14: S9 | B14: =SUMIFS('02_BACKLOG'!$K:$K,'02_BACKLOG'!$B:$B,$A14,'02_BACKLOG'!$I:$I,"Programmer A") -> 41 | C14: ='00_README'!$B$16 -> 80 | D14: =IFERROR(B14/C14,0) -> 0.5125 | E14: =SUMIFS('02_BACKLOG'!$K:$K,'02_BACKLOG'!$B:$B,$A14,'02_BACKLOG'!$I:$I,"Programmer B") -> 44 | F14: ='00_README'!$B$16 -> 80 | G14: =IFERROR(E14/F14,0) -> 0.55 | H14: =B14+E14 -> 85 | I14: =C14+F14 -> 160 | J14: =I14-H14 -> 75 | K14: =COUNTIFS('02_BACKLOG'!$B:$B,$A14,'02_BACKLOG'!$H:$H,"P0",'02_BACKLOG'!$L:$L,"<>Done",'02_BACKLOG'!$L:$L,"<>Deferred") -> 0
A15: S10 | B15: =SUMIFS('02_BACKLOG'!$K:$K,'02_BACKLOG'!$B:$B,$A15,'02_BACKLOG'!$I:$I,"Programmer A") -> 38 | C15: ='00_README'!$B$16 -> 80 | D15: =IFERROR(B15/C15,0) -> 0.475 | E15: =SUMIFS('02_BACKLOG'!$K:$K,'02_BACKLOG'!$B:$B,$A15,'02_BACKLOG'!$I:$I,"Programmer B") -> 38 | F15: ='00_README'!$B$16 -> 80 | G15: =IFERROR(E15/F15,0) -> 0.475 | H15: =B15+E15 -> 76 | I15: =C15+F15 -> 160 | J15: =I15-H15 -> 84 | K15: =COUNTIFS('02_BACKLOG'!$B:$B,$A15,'02_BACKLOG'!$H:$H,"P0",'02_BACKLOG'!$L:$L,"<>Done",'02_BACKLOG'!$L:$L,"<>Deferred") -> 0
A17: TOTAL | B17: =SUM(B5:B15) -> 730 | E17: =SUM(E5:E15) -> 719 | H17: =SUM(H5:H15) -> 1449 | I17: =SUM(I5:I15) -> 1760 | J17: =SUM(J5:J15) -> 311 | K17: =SUM(K5:K15) -> 114

Sheet 04_RELEASE_GATES
A1: Release Gates - Production Launch Cannot Bypass These
A2: Gate status is controlled by evidence, not calendar date. Open related P0 tasks are calculated from 02_BACKLOG.
A4: Gate | B4: Name | C4: Purpose | D4: Pass Criteria / Evidence | E4: Related Task Count | F4: Open Related Tasks | G4: Status | H4: Evidence Link | I4: Owner/Notes
A5: RG-01 | B5: Architecture & Build | C5: Architecture baseline, reproducible builds and safe delivery | D5: ADR-001 accepted; repo/build/container reproducible; deployment artifacts immutable. | E5: =COUNTIF('02_BACKLOG'!$N:$N,"*"&A5&"*") -> 10 | F5: =COUNTIFS('02_BACKLOG'!$N:$N,"*"&A5&"*",'02_BACKLOG'!$L:$L,"<>Done",'02_BACKLOG'!$L:$L,"<>Deferred") -> 10 | G5: In Progress | H5: docs/backlog-audit-2026-09-07.json | I5: 2026-09-07: Nuxt/Nitro/PG kod dhe kontrolle lokale; mungon ADR i stack-ut aktual, Node 24/build aktual, CI me DB dhe immutable deploy.
A6: RG-02 | B6: Tenant Isolation | C6: Zero cross-tenant access | D6: All tenant tables RLS protected; negative cross-tenant suite green. | E6: =COUNTIF('02_BACKLOG'!$N:$N,"*"&A6&"*") -> 8 | F6: =COUNTIFS('02_BACKLOG'!$N:$N,"*"&A6&"*",'02_BACKLOG'!$L:$L,"<>Done",'02_BACKLOG'!$L:$L,"<>Deferred") -> 5 | G6: Not Started | H6: docs/backlog-audit-2026-09-07.json | I6: 2026-09-07: Owner checks në aplikacion ekzistojnë; RLS/runtime role/context dhe suite për të gjitha tabelat nuk janë implementuar.
A7: RG-03 | B7: Auth & RBAC | C7: Identity/authorization trustworthy | D7: Role matrix green; sensitive actions audited; no service credential in browser. | E7: =COUNTIF('02_BACKLOG'!$N:$N,"*"&A7&"*") -> 12 | F7: =COUNTIFS('02_BACKLOG'!$N:$N,"*"&A7&"*",'02_BACKLOG'!$L:$L,"<>Done",'02_BACKLOG'!$L:$L,"<>Deferred") -> 8 | G7: In Progress | H7: docs/backlog-audit-2026-09-07.json | I7: 2026-09-07: Better Auth real dhe origin checks; mungojnë role matrix, sensitive-action audit dhe staging auth suite e plotë.
A8: RG-04 | B8: Meta Readiness | C8: Real customer account integration | D8: Required app access/permissions, redirect/webhook config, reconnect and live eligible-account smoke complete. | E8: =COUNTIF('02_BACKLOG'!$N:$N,"*"&A8&"*") -> 13 | F8: =COUNTIFS('02_BACKLOG'!$N:$N,"*"&A8&"*",'02_BACKLOG'!$L:$L,"<>Done",'02_BACKLOG'!$L:$L,"<>Deferred") -> 13 | G8: Blocked | H8: docs/backlog-audit-2026-09-07.json | I8: 2026-09-07: META_APP_ID/SECRET/LOGIN_CONFIG_ID/REDIRECT_URI mungojnë. Duhet owner Meta App, access review, HTTPS/callbacks dhe non-developer account smoke.
A9: RG-05 | B9: Media Security | C9: Customer assets private and safe | D9: Ownership, signed upload, magic-byte validation, re-encode, EXIF strip and private storage tests green. | E9: =COUNTIF('02_BACKLOG'!$N:$N,"*"&A9&"*") -> 9 | F9: =COUNTIFS('02_BACKLOG'!$N:$N,"*"&A9&"*",'02_BACKLOG'!$L:$L,"<>Done",'02_BACKLOG'!$L:$L,"<>Deferred") -> 9 | G9: In Progress | H9: docs/backlog-audit-2026-09-07.json | I9: 2026-09-07: Private JPEG/Sharp/rights/EXIF tests kalojnë; signed direct upload, variants dhe lifecycle tests mungojnë.
A10: RG-06 | B10: AI Quality & Provenance | C10: AI output grounded and controlled | D10: Golden eval thresholds pass; commercial facts trace to verified evidence; cost budgets enforced. | E10: =COUNTIF('02_BACKLOG'!$N:$N,"*"&A10&"*") -> 20 | F10: =COUNTIFS('02_BACKLOG'!$N:$N,"*"&A10&"*",'02_BACKLOG'!$L:$L,"<>Done",'02_BACKLOG'!$L:$L,"<>Deferred") -> 20 | G10: In Progress | H10: docs/backlog-audit-2026-09-07.json | I10: 2026-09-07: Responses captions/schema/verified-fact context në kod; pa OpenAI credentials/evals/immutable provenance/cost budgets.
A11: RG-07 | B11: Publishing Reliability | C11: No silent/duplicate publishing | D11: Approval, idempotency, retries, reconciliation, 429/5xx/revoked token/DST scenarios pass. | E11: =COUNTIF('02_BACKLOG'!$N:$N,"*"&A11&"*") -> 11 | F11: =COUNTIFS('02_BACKLOG'!$N:$N,"*"&A11&"*",'02_BACKLOG'!$L:$L,"<>Done",'02_BACKLOG'!$L:$L,"<>Deferred") -> 11 | G11: In Progress | H11: docs/backlog-audit-2026-09-07.json | I11: 2026-09-07: Manual calendar i provuar pa Meta; publisher në kod. Mungojnë live publish, retry/backoff, reconciler dhe worker fault matrix.
A12: RG-08 | B12: Billing & Entitlements | C12: Commercial controls correct | D12: Webhook dedupe, subscription transitions, entitlement matrix and usage concurrency tests pass. | E12: =COUNTIF('02_BACKLOG'!$N:$N,"*"&A12&"*") -> 15 | F12: =COUNTIFS('02_BACKLOG'!$N:$N,"*"&A12&"*",'02_BACKLOG'!$L:$L,"<>Done",'02_BACKLOG'!$L:$L,"<>Deferred") -> 14 | G12: In Progress | H12: docs/backlog-audit-2026-09-07.json | I12: 2026-09-07: Trial 72h dhe entitlements me prova PG; nuk ka checkout/subscriptions/billing webhooks/reservation ledger.
A13: RG-09 | B13: Privacy & Data Governance | C13: User data lifecycle controlled | D13: Export/delete/retention paths tested and privacy decisions documented. | E13: =COUNTIF('02_BACKLOG'!$N:$N,"*"&A13&"*") -> 6 | F13: =COUNTIFS('02_BACKLOG'!$N:$N,"*"&A13&"*",'02_BACKLOG'!$L:$L,"<>Done",'02_BACKLOG'!$L:$L,"<>Deferred") -> 6 | G13: In Progress | H13: docs/backlog-audit-2026-09-07.json | I13: 2026-09-07: Privacy UI dhe client JSON export; nuk ka durable export/purge/retention/provider deletion callback dhe legal acceptance.
A14: RG-10 | B14: Observability & Operations | C14: System operable in production | D14: Trace correlation, dashboards, alerts and critical runbooks verified. | E14: =COUNTIF('02_BACKLOG'!$N:$N,"*"&A14&"*") -> 11 | F14: =COUNTIFS('02_BACKLOG'!$N:$N,"*"&A14&"*",'02_BACKLOG'!$L:$L,"<>Done",'02_BACKLOG'!$L:$L,"<>Deferred") -> 11 | G14: In Progress | H14: docs/backlog-audit-2026-09-07.json | I14: 2026-09-07: Audit events/worker heartbeat bazë; pa OpenTelemetry/SLO dashboards/alerts/runbook drills.
A15: RG-11 | B15: Performance & Capacity | C15: Launch load has headroom | D15: At least 3x expected launch load meets API/queue/scheduler targets or blocker fixed. | E15: =COUNTIF('02_BACKLOG'!$N:$N,"*"&A15&"*") -> 6 | F15: =COUNTIFS('02_BACKLOG'!$N:$N,"*"&A15&"*",'02_BACKLOG'!$L:$L,"<>Done",'02_BACKLOG'!$L:$L,"<>Deferred") -> 3 | G15: In Progress | H15: docs/backlog-audit-2026-09-07.json | I15: 2026-09-07: Indekse/pool dhe budget script bazë; pa load 3x/EXPLAIN/Web Vitals aktual. Workspace fetch/PUT mbetet i plotë.
A16: RG-12 | B16: Security Release | C16: No known exploitable launch blocker | D16: ASVS/API security evidence complete; no unresolved critical/high exploitable finding. | E16: =COUNTIF('02_BACKLOG'!$N:$N,"*"&A16&"*") -> 5 | F16: =COUNTIFS('02_BACKLOG'!$N:$N,"*"&A16&"*",'02_BACKLOG'!$L:$L,"<>Done",'02_BACKLOG'!$L:$L,"<>Deferred") -> 5 | G16: In Progress | H16: docs/backlog-audit-2026-09-07.json | I16: 2026-09-07: Disa auth/CSRF/token/media controls; mungon ASVS/security release review me scans aktuale.
... A23: RG-19 | B23: Advanced Content Formats | C23: Growth formats remain capability-aware and publication-safe | D23: Carousel/video/story provider contracts, media validation, idempotency and UX capability fixtures green before enabling per format. | E23: =COUNTIF('02_BACKLOG'!$N:$N,"*"&A23&"*") -> 11 | F23: =COUNTIFS('02_BACKLOG'!$N:$N,"*"&A23&"*",'02_BACKLOG'!$L:$L,"<>Done",'02_BACKLOG'!$L:$L,"<>Deferred") -> 1 | G23: Not Started | H23: docs/backlog-audit-2026-09-07.json | I23: 2026-09-07: Advanced media janë zgjerim deferred pas-GA. Static-only nuk provon carousel/video/story capability gate.

Sheet 05_RISKS
A1: Risk Register
A2: Probability/Impact use 1-5. Score is formula. Review risk weekly from S2 onward and before each production gate.
A4: Risk ID | B4: Risk | C4: Category | D4: Probability | E4: Impact | F4: Score | G4: Level | H4: Owner | I4: Mitigation | J4: Trigger / Leading Indicator | K4: Status | L4: Review Date
A5: R-01 | B5: Meta app review / permission approval takes longer than engineering | C5: External Dependency | D5: 4 | E5: 5 | F5: =D5*E5 -> 20 | G5: =IF(F5>=15,"Critical",IF(F5>=10,"High",IF(F5>=5,"Medium","Low"))) -> Critical | H5: Programmer A | I5: Start review evidence in S2; keep provider mocks/test accounts; make RG-04 explicit launch blocker. | J5: Review status has no progress by end S4. | K5: Open
A6: R-02 | B6: Cross-tenant authorization defect | C6: Security | D6: 2 | E6: 5 | F6: =D6*E6 -> 10 | G6: =IF(F6>=15,"Critical",IF(F6>=10,"High",IF(F6>=5,"Medium","Low"))) -> High | H6: Programmer A | I6: RLS + tenant context + centralized authz + generated negative tests. | J6: Any cross-tenant test or security finding fails. | K6: Open
A7: R-03 | B7: AI creatives look generic or hallucinate facts | C7: Product/AI | D7: 3 | E7: 5 | F7: =D7*E7 -> 15 | G7: =IF(F7>=15,"Critical",IF(F7>=10,"High",IF(F7>=5,"Medium","Low"))) -> Critical | H7: Programmer A | I7: Verified Business Brain, real-asset first, golden evals, deterministic critical text/logo, human approval. | J7: Approval rate <60% or factual eval regression. | K7: Open
A8: R-04 | B8: Publishing duplicates after timeout/retry | C8: Reliability | D8: 2 | E8: 5 | F8: =D8*E8 -> 10 | G8: =IF(F8>=15,"Critical",IF(F8>=10,"High",IF(F8>=5,"Medium","Low"))) -> High | H8: Programmer A | I8: Idempotency keys, attempt ledger, remote reconciliation before retry. | J8: Duplicate in fault-injection or beta. | K8: Open
A9: R-05 | B9: AI/image cost exceeds plan economics | C9: Commercial | D9: 3 | E9: 4 | F9: =D9*E9 -> 12 | G9: =IF(F9>=15,"Critical",IF(F9>=10,"High",IF(F9>=5,"Medium","Low"))) -> High | H9: Programmer A | I9: Entitlements, reservation ledger, model routing, cost dashboards and hard caps. | J9: Variable AI COGS exceeds target for 2 weeks. | K9: Open
A10: R-06 | B10: Two-person team over-engineers architecture | C10: Delivery | D10: 3 | E10: 4 | F10: =D10*E10 -> 12 | G10: =IF(F10>=15,"Critical",IF(F10>=10,"High",IF(F10>=5,"Medium","Low"))) -> High | H10: Both | I10: Modular monolith, no Kubernetes/microservices, task DoR <=16h, ADR trigger for scope changes. | J10: Sprint utilization >95% with spillover twice. | K10: Open
A11: R-07 | B11: Queue backlog at common posting times | C11: Scale | D11: 2 | E11: 4 | F11: =D11*E11 -> 8 | G11: =IF(F11>=15,"Critical",IF(F11>=10,"High",IF(F11>=5,"Medium","Low"))) -> Medium | H11: Programmer A | I11: Queue age SLI, burst load tests, horizontal workers/concurrency controls. | J11: Oldest queue age >2 min sustained. | K11: Open
A12: R-08 | B12: Privacy/retention policy unresolved before launch | C12: Compliance | D12: 3 | E12: 4 | F12: =D12*E12 -> 12 | G12: =IF(F12>=15,"Critical",IF(F12>=10,"High",IF(F12>=5,"Medium","Low"))) -> High | H12: Both | I12: Data inventory, minimization, DSR workflows and explicit legal/privacy review before public rollout. | J12: RG-09 decisions incomplete by S6. | K12: Open
A13: R-09 | B13: Billing provider lacks required merchant/recurring capabilities for Kosovo entity | C13: External Dependency | D13: 3 | E13: 4 | F13: =D13*E13 -> 12 | G13: =IF(F13>=15,"Critical",IF(F13>=10,"High",IF(F13>=5,"Medium","Low"))) -> High | H13: Programmer A | I13: ADR-013 provider selection based on actual merchant/legal capability; BillingGateway keeps core provider-neutral. | J13: No acceptable sandbox/merchant path by mid S5. | K13: Open
A14: R-10 | B14: Provider API/version changes break connector | C14: Integration | D14: 2 | E14: 4 | F14: =D14*E14 -> 8 | G14: =IF(F14>=15,"Critical",IF(F14>=10,"High",IF(F14>=5,"Medium","Low"))) -> Medium | H14: Programmer A | I14: Pinned API version, adapter contracts, capability model, staging test accounts and upgrade checklist. | J14: Provider deprecation notice or contract test fails. | K14: Open
A15: R-11 | B15: UX becomes visually impressive but slower/harder to use | C15: Product/Frontend | D15: 3 | E15: 4 | F15: =D15*E15 -> 12 | G15: =IF(F15>=15,"Critical",IF(F15>=10,"High",IF(F15>=5,"Medium","Low"))) -> High | H15: Programmer B | I15: Nuxt UI primitives, motion budget, reduced motion, performance gates, UAT task success. | J15: Web Vitals/UX regression or beta task completion drops. | K15: Open
A16: R-12 | B16: AI strategy creates plausible but poor marketing advice | C16: AI/Product | D16: 3 | E16: 5 | F16: =D16*E16 -> 15 | G16: =IF(F16>=15,"Critical",IF(F16>=10,"High",IF(F16>=5,"Medium","Low"))) -> Critical | H16: Programmer A | I16: Vertical golden sets, verified inputs, confidence/limitations, human activation and learning evidence. | J16: Strategy UAT/eval falls below threshold. | K16: Open
... A20: R-16 | B20: Support/admin tooling exposes excessive tenant data | C20: Security/Ops | D20: 2 | E20: 5 | F20: =D20*E20 -> 10 | G20: =IF(F20>=15,"Critical",IF(F20>=10,"High",IF(F20>=5,"Medium","Low"))) -> High | H20: Both | I20: Metadata-first admin APIs, no raw secrets, reasoned/audited actions, least privilege. | J20: Admin authz/privacy review finds sensitive unrestricted data. | K20: Open

Sheet 06_TRACEABILITY
A1: Requirements -> Design -> Tasks -> Release Gate Traceability
A2: Use this sheet when a requirement, architecture invariant or release gate changes. It prevents silent gaps between design and implementation.
A4: Requirement ID | B4: Requirement / Invariant | C4: DOCX Section | D4: Task IDs | E4: Release Gate | F4: Verification Evidence
A5: REQ-001 | B5: Organization is tenant/billing/security boundary | C5: 3, 7 | D5: S0-A05;S1-A01;S1-A09 | E5: RG-02 | F5: Cross-tenant RLS/API negative suite
A6: REQ-002 | B6: Central RBAC plus brand scope; UI never authoritative | C6: 3, 8 | D6: S1-A03;S1-A04;S1-B05 | E6: RG-03 | F6: Role matrix + brand-scope E2E
A7: REQ-003 | B7: Social tokens encrypted and never exposed to browser/logs | C7: 8, 9 | D7: S2-A05;S6-A08 | E7: RG-04;RG-12 | F7: OAuth security + log review
A8: REQ-004 | B8: Meta connector capability-aware and versioned | C8: 9 | D8: S2-A04;S2-A06;S6-A09 | E8: RG-04 | F8: Adapter contract + live eligible account smoke
A9: REQ-005 | B9: Gallery originals private; uploads sanitized | C9: 12 | D9: S2-A01;S2-A02;S2-A03 | E9: RG-05 | F9: Upload security fixtures
A10: REQ-006 | B10: Business Brain facts have provenance and verification state | C10: 10 | D10: S1-A06;S3-A04;S3-A05 | E10: RG-06 | F10: Fact lifecycle + evidence tests
A11: REQ-007 | B11: AI model/provider hidden behind capability routing | C11: 11 | D11: S3-A01;S3-A02 | E11: RG-06 | F11: Adapter contract + prompt/model promotion
A12: REQ-008 | B12: Commercial claims cannot use unverified facts | C12: 10-13 | D12: S3-A05;S3-A08;S3-A10;S3-B08 | E12: RG-06 | F12: Golden factuality eval + review provenance
A13: REQ-009 | B13: Content publishable versions are immutable | C13: 13 | D13: S3-A07;S4-A01 | E13: RG-06;RG-07 | F13: Version/state tests
A14: REQ-010 | B14: Publishing is approval-aware, idempotent and reconciled | C14: 13-14 | D14: S4-A01;S4-A04;S4-A06;S4-A07;S4-A09 | E14: RG-07 | F14: Fault-injection publishing suite
A15: REQ-011 | B15: Async side effects use outbox/durable queue | C15: 14, 18 | D15: S0-A08;S4-A03 | E15: RG-01;RG-07 | F15: Crash/duplicate queue tests
... A35: REQ-031 | B35: Public GA requires S0-S8 gates; growth work cannot weaken GA invariants | C35: 52 | D35: S8-A10;S8-A11;S8-B10;S8-B12;S8-A04;S8-B04 | E35: RG-14;RG-17;RG-18 | F35: GA release checklist

Sheet 07_DECISIONS
A1: Architecture Decision Register
A4: ADR | B4: Decision | C4: Status | D4: Required Sprint | E4: Owner | F4: Trigger to Revisit
A5: ADR-001 | B5: Modular monolith + durable workers | C5: Accepted | D5: S0 | E5: Programmer A | F5: Revisit when a bounded context needs independent scale/release/compliance ownership.
A6: ADR-002 | B6: Organization is tenant/billing/security boundary; Brand is sub-entity | C6: Accepted | D6: S0 | E6: Programmer A | F6: Revisit only for explicit reseller/legal tenancy requirement.
A7: ADR-003 | B7: Supabase Auth/Postgres/Storage/Queues; RLS + tenant transaction context | C7: Accepted | D7: S0 | E7: Programmer A | F7: Revisit on measured platform limitation/security requirement.
A8: ADR-004 | B8: Provider ports/adapters; no provider SDK types in domain | C8: Accepted | D8: S0 | E8: Programmer A | F8: Never bypass for convenience.
A9: ADR-005 | B9: Transactional outbox + idempotent queue consumers | C9: Accepted | D9: S0 | E9: Programmer A | F9: Revisit if event volume justifies external bus.
A10: ADR-006 | B10: Verified Business Brain + content fact/asset provenance | C10: Accepted | D10: S1 | E10: Programmer A | F10: Core product invariant.
A11: ADR-007 | B11: AI capability routing + prompt versioning + golden eval | C11: Accepted | D11: S3 | E11: Programmer A | F11: Model change requires eval/canary, not ADR unless architecture changes.
A12: ADR-008 | B12: Private media + immutable derived assets + deterministic critical text/logo | C12: Accepted | D12: S2 | E12: Programmer B | F12: Revisit for video pipeline.
A13: ADR-009 | B13: Immutable content versions + approval state machine + publish reconciliation | C13: Accepted | D13: S3/S4 | E13: Programmer A | F13: Core reliability invariant.
A14: ADR-010 | B14: Provider-neutral entitlements/usage ledger | C14: Accepted | D14: S1 | E14: Programmer A | F14: Provider selection does not change core.
A15: ADR-011 | B15: OpenAPI-generated TS client + stable Problem error codes | C15: Accepted | D15: S0 | E15: Programmer B | F15: Breaking API requires version/compatibility plan.
... A30: AUD-2026-05 | B30: Observed stack: Nitro API, Better Auth, direct PostgreSQL and in-process publisher; original FastAPI/Supabase/outbox baseline differs. | C30: Needs ADR review | D30: Before GA | E30: Engineering owner | F30: Reconcile deployment boundaries/toolchain/API contracts/RLS. This audit does not waive enterprise security requirements.

Sheet 08_SOURCES
A1: Current Technical Sources / Standards
A2: Revalidate provider/API versions at implementation time. URLs are intentionally plain text and clickable.
A4: Source | B4: URL | C4: As of | D4: Used For
A5: Nuxt 4 guide / v4.5.x | B5: https://nuxt.com/docs/4.x/guide/ | C5: 2026-09-05 | D5: Frontend framework baseline; Nuxt 3 EOL has passed.
A6: Nuxt security releases | B6: https://nuxt.com/blog/v4-5-security | C6: 2026-09-05 | D6: Patch line/security maintenance.
A7: FastAPI in Containers | B7: https://fastapi.tiangolo.com/deployment/docker/ | C7: 2026-09-05 | D7: Container deployment pattern; Python 3.14 example.
A8: Python 3.14 documentation | B8: https://docs.python.org/3/ | C8: 2026-09-05 | D8: Stable Python 3.14 baseline.
A9: Supabase Production Checklist | B9: https://supabase.com/docs/guides/deployment/going-into-prod | C9: 2026-09-05 | D9: RLS/security/load/production controls.
A10: Supabase Queues | B10: https://supabase.com/docs/guides/queues | C10: 2026-09-05 | D10: Postgres-native durable pgmq queues.
A11: Meta Instagram API | B11: https://www.postman.com/meta/instagram/documentation/6yqw8pt/instagram-api | C11: 2026-09-05 | D11: Professional account access, media/insights/publishing.
A12: Meta Instagram publishing | B12: https://www.postman.com/meta/instagram/documentation/6yqw8pt/instagram-api | C12: 2026-09-05 | D12: Publishing flow and public media fetch requirement.
A13: OpenAI API Reference - Responses | B13: https://developers.openai.com/api/reference/ | C13: 2026-09-05 | D13: Structured responses/orchestration.
A14: GPT-Image-2 | B14: https://developers.openai.com/api/docs/models/gpt-image-2 | C14: 2026-09-05 | D14: Image generation/editing; snapshot pinning.
A15: OWASP ASVS | B15: https://owasp.org/www-project-application-security-verification-standard/ | C15: 2026-09-05 | D15: ASVS 5.0.0 security verification baseline.
... A25: OpenAI model catalog | B25: https://platform.openai.com/docs/models | C25: 2026-09-05 | D25: Capability routing and current text/image model catalog; snapshot revalidation.

Sheet 09_UI_ARCHITECTURE
A1: Frontend / UX Architecture Control Sheet
A2: Rule | B2: Specification | C2: Release Evidence
A3: Primary stack | B3: Nuxt 4.5.x + Node 24 LTS + TypeScript strict + Nuxt UI v4 + Tailwind theme tokens + Motion for Vue | C3: Build/typecheck + source review
A4: Component policy | B4: Use Nuxt UI primitives first; custom component only when composition cannot satisfy documented requirement | C4: Component inventory review
A5: Navigation | B5: DashboardGroup/Sidebar/Navbar/Toolbar/Search; responsive mobile drawer/toggle; org/brand context persistent | C5: Cross-device E2E
A6: Motion | B6: Purposeful only; reduced-motion mandatory; no blocked input; lazy-load heavy landing motion | C6: A11y/performance/visual
A7: Data | B7: Generated typed API client; no provider SDK or service-role in browser; server remains authority | C7: Static review + E2E
A8: Drafts | B8: Autosave + revision conflict handling; no silent overwrite/data loss | C8: Fault E2E
A9: Errors | B9: Typed actionable errors; request ID for support; no secrets/internal stack in UI | C9: Fault fixtures
A10: Responsive | B10: 360px+ critical workflows; calendar/editor adapt, not shrink blindly | C10: Mobile E2E
A11: Accessibility | B11: Keyboard/focus/labels/live status/reduced motion; no serious/critical release findings | C11: axe + manual
A12: Performance | B12: SSR public pages; route splitting; lazy editor/chat/charts/motion; image thumbnails; observed bundle budgets | C12: Nuxt analyze + Web Vitals

Sheet 10_ROUTE_MAP
A1: Area | B1: Route | C1: Page / Purpose | D1: Primary Components | E1: Auth / Scope | F1: GA/Growth
A2: Public | B2: / | C2: Landing | D2: Header; PageHero; PageSection; PageFeature; PageCTA; Footer | E2: Public | F2: GA
A3: Public | B3: /pricing | C3: Pricing | D3: PricingTable; Accordion; PageCTA | E3: Public | F3: GA
A4: Public | B4: /security | C4: Security/trust | D4: PageHeader; PageSection; Accordion | E4: Public | F4: GA
A5: Auth | B5: /login | C5: Login | D5: AuthForm; Alert | E5: Public/anon | F5: GA
A6: Auth | B6: /signup | C6: Signup | D6: AuthForm; Form | E6: Public/anon | F6: GA
A7: App | B7: /app/:org/:brand/overview | C7: Marketing HQ | D7: Dashboard components; Card; Progress; Drawer | E7: Member + brand scope | F7: GA
A8: App | B8: .../strategy | C8: Strategy Center | D8: Tabs; Editor; Slideover; Modal | E8: Marketer+ | F8: GA
A9: App | B9: .../campaigns | C9: Campaigns | D9: Table; Timeline; Drawer; Form | E9: Marketer+ | F9: GA
A10: App | B10: .../content | C10: Content Studio | D10: Table/Grid; Tabs; Badge; Drawer | E10: Marketer+ | F10: GA
A11: App | B11: .../content/new | C11: Create content | D11: ChatPrompt; Editor; FileUpload; Tabs; Modal | E11: Marketer+ | F11: GA
A12: App | B12: .../calendar | C12: Calendar | D12: Calendar/domain view; Popover; Drawer | E12: Marketer+ | F12: GA
... A21: Growth | B21: .../reports | C21: Client reports | D21: PageSection; Card; Table | E21: Viewer+ | F21: Growth

Sheet 11_COMPONENT_MAP
A1: Category | B1: Nuxt UI Component / Primitive | C1: Use in Product | D1: Customization Policy | E1: Motion Policy
A2: Dashboard | B2: DashboardGroup / Sidebar / Navbar / Toolbar / Search | C2: Authenticated shell and navigation | D2: Theme + slots; no fork | E2: Sidebar/layout subtle only
A3: Landing | B3: PageHero / PageSection / PageFeature / PricingTable / PageCTA | C3: Marketing pages | D3: Brand tokens + content composition | E3: Scroll/hero purposeful, lazy
A4: AI Chat | B4: ChatMessages / ChatPrompt / ChatTool / ChatPalette | C4: Marketing copilot | D4: Custom tool cards allowed | E4: Status transitions; no fake typing delay
A5: Editor | B5: Editor / EditorToolbar | C5: Captions/long text | D5: Domain controls around editor | E5: Minimal
A6: Forms | B6: Form / FormField / Input / SelectMenu / InputTags / Switch | C6: Onboarding/settings | D6: Shared validation/error mapping | E6: Micro interaction only
A7: Media | B7: FileUpload / Progress / Card / Slideover | C7: Gallery/video upload | D7: Custom preview/crop domain widgets | E7: Progress/reorder only
A8: Data | B8: Table / Timeline / Empty / Skeleton / ScrollArea | C8: Admin/analytics/history | D8: Server pagination; accessible summary | E8: Loading transitions only
A9: Overlay | B9: Modal / Drawer / Slideover / Popover / Toast | C9: Confirm/detail/mobile | D9: Consistent sizes/escape/focus | E9: Enter/exit, reduced motion
A10: Navigation | B10: CommandPalette / Breadcrumb / Tabs / Stepper | C10: Search/onboarding/settings | D10: No ad-hoc nav component | E10: Small layout transition

Sheet 12_TEST_MATRIX
A1: Area | B1: Unit | C1: Integration/Contract | D1: E2E/Fault | E1: Release Evidence
A2: Tenancy/Auth | B2: Policy/state rules | C2: RLS + API authorization matrix | D2: Cross-tenant negative journeys | E2: RG-02/RG-03
A3: Meta | B3: Adapter taxonomy | C3: OAuth/webhook/publish contracts | D3: revoked token/429/5xx/timeout/duplicate | E3: RG-04/RG-07
A4: AI | B4: schema/policy/cost rules | C4: provider adapter snapshots | D4: golden + injection + cost loop | E4: RG-06/RG-16/RG-18
A5: Media | B5: validation/crop rules | C5: storage/worker contracts | D5: bad file/oversize/retry | E5: RG-05
A6: Frontend | B6: composables/components | C6: API error mapping | D6: Playwright desktop/mobile + visual + a11y | E6: RG-17
A7: Billing | B7: state machine | C7: webhook replay | D7: failed/out-of-order/upgrade/downgrade | E7: RG-08
A8: DR/Ops | B8: runbook helpers | C8: backup/restore configuration | D8: restore + queue/provider fault campaign | E8: RG-10/RG-13
A9: Growth formats | B9: format validator | C9: provider capability contract | D9: carousel/video partial failure/duplicate | E9: RG-19

Sheet 13_AI_EVALS
A1: Eval Dimension | B1: Minimum Release Expectation | C1: Automated Evidence | D1: Human Evidence | E1: Blocking?
A2: Factuality | B2: No unsupported hard commercial claim in release golden set | C2: fact_ref validator + golden cases | D2: Vertical sample review | E2: Yes
A3: Safety | B3: All BLOCK fixtures blocked; WARN explainable | C3: policy decision fixtures | D3: Policy reviewer sample | E3: Yes
A4: Prompt injection | B4: No unauthorized tool/policy change from untrusted content | C4: adversarial suite | D4: Targeted red-team review | E4: Yes
A5: Brand adherence | B5: Meets agreed per-vertical score | C5: tone/banned-term checks + rubric model where approved | D5: Brand fit 1-5 sample | E5: Yes
A6: Strategy usefulness | B6: Majority accepted without full rewrite in UAT | C6: structured completeness checks | D6: Dental/restaurant/real-estate UAT | E6: Yes for GA
A7: Visual integrity | B7: Exact critical text/logo; no unacceptable asset distortion | C7: deterministic compositor/image QA | D7: Visual sample | E7: Yes
A8: Learning | B8: Recommendation cites metrics and uncertainty | C8: metric_ref validation | D8: Analyst/product review | E8: Yes
A9: Cost | B9: Representative plan workload stays inside approved envelope | C9: usage replay/reservation ledger | D9: Commercial owner review | E9: Yes

Sheet 14_AUDIT_2026-09-07
A1: Rrit · Gjendja reale e 185 task-eve
A2: Rishikim i thelluar 2026-09-07 · 133 skedarë / 185 task-e · prova lokale; jo pranim Production GA.
A4: Statusi kontraktual | B4: Task-e | C4: Kuptimi
A5: In Review | B5: =COUNTIF('02_BACKLOG'!$L$5:$L$189,A5) -> 23 | C5: Implementimi kryesor i scope-it aktual ekziston; mbeten pranim/teste të plota dhe release gates. Nuk barazohet me Done.
A6: In Progress | B6: =COUNTIF('02_BACKLOG'!$L$5:$L$189,A6) -> 90 | C6: Ka implementim të pjesshëm; Z tregon realizimin, AA hapat e mbetur, AB provën e kërkuar, AC rezultatin aktual dhe AD kodin/gjetjet.
A7: Not Started | B7: =COUNTIF('02_BACKLOG'!$L$5:$L$189,A7) -> 35 | C7: Nuk u gjet implementim/artefakt pranimi për kërkesën. Kriteri mbetet i hapur.
A8: Blocked | B8: =COUNTIF('02_BACKLOG'!$L$5:$L$189,A8) -> 2 | C8: Meta App/access/credentials mungojnë; krijimi dhe verifikimi kërkon pronarin e llogarisë Meta.
A9: Deferred | B9: =COUNTIF('02_BACKLOG'!$L$5:$L$189,A9) -> 35 | C9: Shtyrë nga scope-i posts-only ose zgjerim pas-GA. Detyra/ID/estimates ruhen; nuk është përfunduar.
A10: Done | B10: =COUNTIF('02_BACKLOG'!$L$5:$L$189,A10) -> 0 | C10: Asnjë task i plotë origjinal nuk ka të gjitha provat dhe gates për pranim formal. Funksionaliteti real lokal është shënuar veçmas.
A11: Gjithsej | B11: =SUM(B5:B10) -> 185 | C11: 185 ID origjinale; asnjë task nuk është fshirë ose numëruar dy herë.
A14: Faza e përdorimit | B14: Aplikacion funksional lokal me llogari/PostgreSQL dhe rrjedhë manuale të postimeve. Meta live, AI live, pagesat dhe gatishmëria enterprise nuk janë pranuar.
A15: Prova: unit + PostgreSQL | B15: 33/33 kaluan: hq-deep-audit-unit.log. Schema testuese nga migrimet, trial/identities/expiry, media, validation, crypto/transport, workspace/DST/auth config.
A16: Prova: browser | B16: 8/8 në dy suite: live rerun 4/4 dhe registration/optional-meta 4/4. Chromium 1440px/390px, përfshirë axe në 7 faqe dashboard-i. Log-et: hq-deep-audit-live-e2e-rerun.log dhe hq-deep-audit-registration-meta-e2e.log.
A17: Prova: TypeScript / lint | B17: Full eslint . dhe TypeScript app/server kaluan: hq-deep-audit-lint.log, hq-deep-audit-app-types.log, hq-deep-audit-server-types.log. Pas DA-17 kaloi edhe eslint i live.spec.ts.
A18: Dështimi i regjistruar dhe korrigjimi | B18: live.spec.ts fillimisht 2 passed/2 failed: kërkonte numrin 2 kur pamja kompakte shfaq vetëm numrin aktual. DA-17 korrigjon selektorin te Next Page pa hequr assertions; rerun 4/4. Raporti i vjetër demo në VALIDATION.md nuk zëvendëson këto rezultate.
A19: Mjedisi aktual | B19: Node lokal raporton v26.5.0; .nvmrc nuk gjendet në disk. README/CI përmend Node 24. Kërkohet riprodhim i toolchain-it të synuar; konfigurimet sekrete nuk janë kopjuar në workbook.
A20: Konfigurime që mungojnë | B20: META_APP_ID, META_APP_SECRET, META_LOGIN_CONFIG_ID, META_REDIRECT_URI, OPENAI_API_KEY, OPENAI_MODEL dhe PUBLISHING_ENABLED mungojnë. Nuk u krye publikim ose AI generation live gjatë auditit.
A21: Meta opsionale | B21: Miratimi dhe kalendari përdorin scope content/manual. Lidhja Meta kërkohet për import dhe publikim real. Një lidhje e mëvonshme nuk e bën automatik një postim manual.
A22: Trial / euro / pa demo | B22: 72 orë nga krijimi i biznesit, pa zgjatje në retry; ledger për email/browser/social identities. Browser cookie nuk është hardware fingerprint. Çmimet vijnë nga DB në EUR, por janë propozime pa checkout aktiv.
A23: Ndryshim arkitekture | B23: Backend-i aktual është Nitro + Better Auth + PostgreSQL; plani FastAPI/Supabase dhe kërkesat RLS/outbox nuk janë realizuar siç specifikohen. AUD-2026-05 kërkon ADR; siguria nuk hiqet nga scope-i.
A24: Leximi dhe ndryshimet e auditit | B24: 133 skedarë first-party, 10451 rreshta, përfshirë 7 migrimet, server/app/shared/test/config. 185 task-e me realizim/mbetje/prova veçmas; 17 gjetje DA-01..DA-17. Ndryshimi i vetëm në kod është selektori i testit DA-17.
A25: Backup para rishikimit të dytë | B25: docs/backups/AI_Marketing_Platform_Engineering_Master_Backlog_2_Developers_v1.1.before-deep-audit-2026-09-07.xlsx
... A32: S0-A03 production-grade toolchain implementation | B32: Nitro/TypeScript mapping, exact Node/npm pins, lock enforcement, deterministic tests, pre-commit, shared CI commands and Docker clean-room gate implemented. 24 unit + 28 integration tests and production build passed; hosted CI/reviewer RG-01 sign-off remains.

Sheet 15_GJETJET
A1: ID | B1: Prioriteti | C1: Gjetja | D1: Task-et | E1: Kodi | F1: Shkaku / sjellja | G1: Çfarë mbetet | H1: Prova e korrigjimit | I1: Niveli i evidencës | J1: Statusi pas implementimit | K1: Evidenca e re / kufiri
A2: DA-01 | B2: P1 | C2: Afati i Instagram-it fillon nga krijimi i punës | D2: S4-A04, S4-A05, S4-A09, S8-A11 | E2: apps/web/server/utils/publishing.ts:235 | F2: Në IN_PROGRESS, kufiri njëorësh matet nga publication_jobs.created_at. Një punë e planifikuar më shumë se një orë përpara mund të dështojë në kontrollin e parë të container-it të sapokrijuar. | G2: Ruaj fillimin/afatin e përpunimit të container-it veçmas nga krijimi i orarit dhe përdore gjatë poll/restart. | H2: Fixture: job i krijuar dje, container i krijuar tani, IN_PROGRESS pastaj FINISHED; publikim vetëm një herë. Provo veçmas skadimin real të container-it. | I2: Gjetje nga rruga e kodit; nuk u ekzekutua kundrejt Meta-s. | J2: Resolved locally | K2: container_started_at + 59/61 minute boundary test; live Meta remains a task gate.
A3: DA-02 | B3: P1 | C3: Worker-i merr vetëm një punë çdo 30 sekonda | D3: S4-A03, S5-A09, S6-A07 | E3: apps/web/server/plugins/publisher.ts:15 apps/web/server/utils/publishing.ts:160 | F3: Çdo tick merr një biznes sipas ID-së dhe një punë. Intervali vendos rreth dy marrje pune/minutë për proces para vonesave të provider-it; nuk ka batch/concurrency të konfigurueshme ose drejtësi sipas orarit global. | G3: Përpuno batch të kufizuar me concurrency të kontrolluar, renditje të drejtë të punëve të vonuara dhe metrika queue-age. | H3: Burst nga disa biznese në të njëjtin orar, dy worker-a, pa dyfishime ose uri të një biznesi; mat vonesën ndaj objektivit të planifikuar. | I3: Kufiri rrjedh nga intervali dhe LIMIT 1; nuk është benchmark i matur. | J3: Partially addressed | K3: Bounded batch, oldest-due fairness, configurable poll and queue-age readiness; multi-worker load proof remains.
A4: DA-03 | B4: P1 | C4: Postimi failed nuk ka veprim rikuperimi në editor | D4: S4-B04, S4-B06, S7-B03, S7-B08 | E4: apps/web/app/components/ContentEditor.vue:150 apps/web/app/components/ContentEditor.vue:427 apps/web/app/components/ContentEditor.vue:467 apps/web/server/utils/publishing.ts:115 | F4: Failed shfaq checkbox kontrolli, por butonat Mirato/Kthe në draft shfaqen vetëm për review; editori lejon ndryshim vetëm në draft/review. Skema lejon failed→approved, por UI nuk e ekspozon rrugën. | G4: Shto rikuperim sipas kodit të dështimit me kontroll të freskët dhe konfirmim; mbaje uncertain të bllokuar derisa të zgjidhet rezultati. | H4: E2E për failed të sigurt, media/auth error dhe uncertain; përdoruesi arrin korrigjimin pa shkaktuar publikim të dyfishtë. | I4: Gjetje statike nga kushtet e template-it dhe state machine; nuk është riprodhim me publikim real. | J4: Partially addressed | K4: Failed can return to draft or re-approval; full provider error-code E2E remains.
A5: DA-04 | B5: P1 | C5: Uncertain mund të bllokojë rilidhjen pas disconnect | D5: S2-B08, S4-A06, S4-B06, S7-A06 | E5: apps/web/server/api/meta/disconnect.post.ts:26 apps/web/server/api/meta/callback.get.ts:38 apps/web/server/api/meta/select.post.ts:50 | F5: Disconnect ruan punën uncertain por fshin lidhjen. Callback/select refuzojnë lidhje kur ekziston uncertain. Mungon reconciler/API operative që ta zgjidhë gjendjen. | G5: Përfundo zgjidhjen e rezultatit me prova nga provider-i dhe një rrugë të audituar rikuperimi/rilidhjeje që nuk ridërgon verbërisht postimin. | H5: Timeout pas efektit të jashtëm → uncertain → disconnect → verifikim rezultati → reconnect; ruaj identitetin e target-it dhe mos dyfisho. | I5: Sekuencë e identifikuar nga kushtet server; prova fault-injection mbetet e hapur. | J5: Resolved locally | K5: Timeout-after-side-effect provider fixture reconciles one exact result without a second write; live Meta remains a release gate.
A6: DA-05 | B6: P1 | C6: Historiku i importuar nuk lidhet me llogarinë burimore | D6: S2-A07, S2-B06, S2-B07, S3-A05 | E6: apps/web/server/api/meta/sync.post.ts:82 apps/web/server/api/meta/posts.get.ts:23 apps/web/server/api/meta/select.post.ts:59 | F6: Social posts ruhen sipas business/channel/provider_id pa source account. Ndryshimi i faqes nuk i arkivon/fshin importet e vjetra; query dhe konteksti AI mund t'i përziejnë me historikun e faqes së re. | G6: Ruaj source account dhe versionin e lidhjes; filtro/arkivo importet kur ndryshon faqja dhe rifresko cursor-in/kontekstin e AI. | H6: Import nga faqja A, lidh faqen B, import i ri: lista dhe konteksti i B përmbajnë vetëm burimet e zgjedhura, me provenance të ruajtur. | I6: Gjetje nga skema dhe query; nuk u provua ndërrim me dy faqe reale Meta. | J6: Resolved locally | K6: source_account_id migration/query/AI filtering and two-source DB test pass; live two-page test remains a release gate.
A7: DA-06 | B7: P1 | C7: Login dhe recovery varen nga gatishmëria e regjistrimit | D7: S0-B04, S6-B05, S8-B12 | E7: apps/web/app/components/AuthSurface.vue:74 apps/web/server/api/capabilities.get.ts:23 | F7: Submit kontrollon capabilities.registration për të gjitha mënyrat e auth. Registration kërkon edhe trial policy/config; dështimi i tyre mund të ndalë nga UI hyrjen/rikuperimin e një llogarie ekzistuese. | G7: Ndaj gatishmërinë e login, signup, verification dhe reset; problemi i trial-it të ndalë vetëm veprimin që varet prej tij. | H7: Llogari ekzistuese me trial policy të padisponueshme: login lejohet kur auth punon; signup jep gabim të qartë; recovery ndjek vetëm gatishmërinë e emailit/auth. | I7: Gjetje statike. Testet lokale të auth kalojnë në konfigurimin normal, jo në këtë fault mode. | J7: Resolved locally | K7: Login/signup/recovery readiness split and degradation tests pass.
A8: DA-07 | B8: P1 | C8: Historiku nuk është snapshot i plotë immutable | D8: S3-A07, S3-B06, S4-A01, S4-B01, S4-B07 | E8: apps/web/server/api/workspaces/[id].put.ts apps/web/shared/schemas/workspace.ts apps/web/server/utils/post-validation.ts | F8: Historiku ruan caption/version/at, jo fotografinë, titullin, kanalin dhe provenance të çdo versioni. Statuset gjithashtu rrisin versionin; fingerprint-i i validimit lidhet me përmbajtjen, jo me një content_version immutable. | G8: Ndaj content revision nga workflow state; ruaj snapshot të plotë dhe approval/validation/attempt records që referojnë të njëjtin version. | H8: Ndrysho fotografi/tekst/kanal pas miratimit; versioni i vjetër mbetet identik dhe approval i vjetër nuk autorizon versionin e ri; provo konkurencën. | I8: Struktura dhe guards u lexuan; stale-content checks kalojnë në suite, por nuk provojnë historik immutable të plotë. | J8: Resolved locally | K8: Full immutable snapshots and version-bound validation/approval/attempt records with tenant FKs pass DB tests.
A9: DA-08 | B9: P1 | C9: Workflow CI nuk përgatit varësitë e backend-it aktual | D9: S0-A09, S0-B07, S0-B08, S4-B08, S8-B01 | E9: .github/workflows/frontend.yml:18 apps/web/tests/integration/server.test.ts apps/web/playwright.config.ts:29 | F9: CI thërret integration/E2E pa provisionim PostgreSQL, SMTP, konfigurim testues dhe migrime. E2E me TEST_BASE_URL përdor preview; kjo nuk i siguron shërbimet. Kalimi lokal nuk provon required checks hosted. | G9: Përgatit services dhe kredenciale vetëm testuese, zbato migrimet, bëj cleanup të fixture-ve dhe verifiko një run hosted e një PR që dështon me qëllim. | H9: CI nga checkout i pastër kalon testet me DB; heqja e një guard-i e bllokon merge-in. Arkivo raportet pa sekrete. | I9: Workflow u lexua; nuk u ekzekutua hosted CI. Workspace nuk përmban .git. | J9: Partially addressed | K9: CI now provisions PostgreSQL/env/migrations/readiness; hosted required-check proof remains.
A10: DA-09 | B10: P2 | C10: Pagination-i i workspace-it është vetëm në klient | D10: S2-B01, S3-B01, S5-A09, S6-B13, S8-B10 | E10: apps/web/app/composables/usePagination.ts:12 apps/web/app/composables/useWorkspace.ts:27 apps/web/app/composables/useWorkspace.ts:54 apps/web/app/layouts/dashboard.vue:102 | F10: Listat e postimeve/galerisë dhe kërkimi global ngarkojnë workspace-in e plotë; ruajtjet dërgojnë snapshot të plotë. Importet Meta kanë query pagination të veçantë. Prova me 13 postime kalon, por nuk është provë ngarkese. | G10: Shto API të kufizuara për lista/kërkim dhe commands të veçanta për mutacione, me revision/idempotency dhe thumbnails sipas nevojës. | H10: Fixture 500+ asset dhe 1000 postime: mat bytes/p95/memorien; filtër/cursor nuk kalon tenant-in dhe ndryshimi i një postimi nuk rishkruan gjithë listën. | I10: Pagination desktop/mobile kaloi në rerun; shkallëzimi nuk u mat. | J10: Open | K10: Server-side list/command APIs and load evidence remain.
A11: DA-10 | B11: P1 | C11: Eksporti JSON nuk është arkiv i rikthyeshëm i biznesit | D11: S6-A04, S7-B07, S8-A10 | E11: apps/web/app/composables/useWorkspace.ts:124 apps/web/server/api/media/[id].get.ts | F11: Eksporti përmban workspace dhe drafts të skedës; fotografitë referohen me URL private dhe nuk futen si bytes. Importet sociale/audit/identity dhe manifest/checksums nuk janë pjesë e këtij eksporti. | G11: Përcakto kontratën e eksportit; krijo server job me manifest dhe media të autorizuara, expiry/recent-auth dhe përfshirje të dokumentuar të të dhënave. | H11: Eksport me fotografi/import/history; kontrollo manifest/checksum dhe qasjen/expiry nga llogari tjetër. Mos e paraqit JSON-in aktual si backup të plotë. | I11: Përmbajtja e funksionit exportData u lexua; nuk është provuar eksport i plotë serveri. | J11: Open | K11: Restorable server export with media/manifest remains.
A12: DA-11 | B12: P1 | C12: Retention dhe tërheqja e të drejtave kanë lifecycle të paplotë | D12: S7-A05, S6-A05, S2-B03, S8-A10 | E12: apps/web/server/utils/trials.ts:30 apps/web/database/migrations/0004_trials_and_social.sql apps/web/server/api/workspaces/[id].put.ts apps/web/app/pages/app/[org]/[brand]/gallery.vue:298 | F12: Cookie ka afat fiks 365 ditë; mungon purge për trial claims dhe të dhëna të tjera. Asset-et në përdorim nuk mund të hiqen dhe një rights=false refuzohet për referenca ekzistuese; UI e galerisë nuk ofron tërheqje të drejtash. | G12: Përcakto retention/consent policy, zbato afatet me jobs dhe rrugën e tërheqjes së të drejtave që ndalon përdorimin e ardhshëm pa falsifikuar historikun. | H12: Revoko të drejtat e asset-it në postim të planifikuar, verifiko bllokimin e publikimit; provo purge/resume dhe përjashtimet e dokumentuara të ruajtjes. | I12: Gjetje statike; nuk pretendohet se API lejon revokim dhe pastaj publikim me validation të vjetër. Aktualisht vetë ndryshimi refuzohet. | J12: Partially addressed | K12: Versioned retention batch and enforceable rights withdrawal exist; purge/deletion callbacks and legal approval remain.
... A18: DA-17 | B18: P2 | C18: Testi i pagination-it kërkonte një numër të fshehur nga konfigurimi | D18: S0-B08, S3-B01, S4-B08 | E18: apps/web/tests/e2e/live.spec.ts:161 apps/web/app/components/ListPagination.vue:24 | F18: sibling-count=0/show-edges=false shfaq vetëm numrin aktual; testi kërkonte butonin 2. Selektori u ndryshua te Next Page pa hequr assertion-in 11–13 nga 13. | G18: Gjetja e testit është korrigjuar. Mbetet lokalizimi i emrave aksesues Next Page/Page 2 dhe prova hosted CI e task-eve përkatëse. | H18: Rerun live.spec.ts: 4/4 desktop/mobile, përfshirë pagination dhe axe në 7 faqe dashboard-i. | I18: E riprodhuar dhe e korrigjuar; hq-deep-audit-live-e2e.log (2 dështime) dhe hq-deep-audit-live-e2e-rerun.log (4 kalime). | J18: Resolved locally | K18: Pagination locator fixed and combined E2E passes 8/8; hosted CI/localized primitive labels remain.

Sheet 16_HANDOFF_2_DEV
A1: Task ID | B1: Sprint | C1: Priority | D1: Status formal | E1: Gjendja e kodit | F1: Owner | G1: Reviewer | H1: Task | I1: Hapi i ardhshëm | J1: Release gate | K1: Prova e kërkuar
A2: S0-A01 | B2: S0 | C2: P0 | D2: In Review | E2: Kryer në kod — pret pranim/gate | F2: Programmer A | G2: Programmer B | H2: Record ADR-001 modular monolith baseline | I2: Mbeten architecture review checklist, prova e deployment-it të ndarë dhe RG-01. Follow-up-et RLS/runtime-role/observability të ADR-002 nuk janë gates të kaluara. | J2: RG-01 | K2: Prova e kërkuar nga backlog-u: Architecture review checklist Kriteri për t'u verifikuar (nuk deklarohet i kaluar): ADR accepted; no unresolved architecture blocker; repo links ADR from README. DA-13: Content review në local bypass dhe public verification, pa përshkrime të shërbimeve të paaktivizuara si aktive; operatori pranon versionin publik. Pranimi kërkon edhe gate-et: RG-01. Asnjë gate nuk është shënuar Passed nga ky audit.
A3: S0-A02 | B3: S0 | C3: P0 | D3: In Review | E3: Kryer në kod — pret pranim/gate | F3: Programmer A | G3: Programmer B | H3: Bootstrap backend/worker packages | I3: Duhet container/process smoke me publisher të aktivizuar, deployment i veçantë i worker-it dhe RG-01; Meta App mungon për një start real publishing. | J3: RG-01 | K3: Prova e kërkuar nga backlog-u: pytest smoke + container smoke Kriteri për t'u verifikuar (nuk deklarohet i kaluar): API/worker start locally; module import rule documented; /health/live returns 200. Pranimi kërkon edhe gate-et: RG-01. Asnjë gate nuk është shënuar Passed nga ky audit.
A4: S0-A04 | B4: S0 | C4: P0 | D4: In Review | E4: Kryer në kod — pret pranim/gate | F4: Programmer A | G4: Programmer B | H4: Bootstrap PostgreSQL environments and migrations | I4: Ekzekuto migration dry-run në staging me role të ndara dhe regjistro RG-01; kjo kërkon mjedisin e hostuar. | J4: RG-01 | K4: Prova e kërkuar: empty-database migration smoke, runtime DDL-deny, staging dry-run dhe RG-01.
A5: S0-A07 | B5: S0 | C5: P0 | D5: In Review | E5: Kryer në kod — pret pranim/gate | F5: Programmer A | G5: Programmer B | H5: Verify Better Auth sessions in Nitro | I5: Ekzekuto suite-n në hosted CI/public staging dhe regjistro security review/RG-03. | J5: RG-03 | K5: Prova e kërkuar: valid/forged/revoked/expired session E2E, origin rejection dhe RG-03.
A6: S0-A08 | B6: S0 | C6: P0 | D6: In Review | E6: Kryer në kod — pret pranim/gate | F6: Programmer A | G6: Programmer B | H6: Create durable queue/outbox skeleton | I6: Ekzekuto hosted CI/container failure rehearsal dhe regjistro RG-01; adapterët me side-effect të jashtëm vazhdojnë të përdorin idempotency/reconciliation specifik. | J6: RG-01 | K6: Prova e kërkuar: queue duplicate/crash/concurrency tests, container smoke dhe RG-01.
A7: S0-B01 | B7: S0 | C7: P0 | D7: In Review | E7: Kryer në kod — pret pranim/gate | F7: Programmer B | G7: Programmer A | H7: Bootstrap Nuxt 4 application | I7: Duhet npm ci + production build nga checkout i pastër me Node 24 dhe RG-01. Makina e këtij auditimi po përdor Node 26.5.0. | J7: RG-01 | K7: Prova e kërkuar nga backlog-u: nuxt build + typecheck Kriteri për t'u verifikuar (nuk deklarohet i kaluar): Clean install/build/typecheck passes from lockfile; Node 24 LTS documented; no secret runtime config exposed client-side. Pranimi kërkon edhe gate-et: RG-01. Asnjë gate nuk është shënuar Passed nga ky audit.
A8: S0-B03 | B8: S0 | C8: P0 | D8: In Review | E8: Kryer në kod — pret pranim/gate | F8: Programmer B | G8: Programmer A | H8: Build authenticated application shell | I8: Për scope-in me një biznes për pronar, kodi është implementuar. Mbeten pranim i plotë keyboard/tablet/a11y dhe RG-14; multi-org switcher është jashtë rrjedhës aktuale. | J8: RG-14 | K8: Prova e kërkuar nga backlog-u: component + Playwright shell smoke Kriteri për t'u verifikuar (nuk deklarohet i kaluar): Desktop/tablet/mobile shell is keyboard accessible; navigation persists correctly; active org/brand context visible; no layout shift blocker. Pranimi kërkon edhe gate-et: RG-14. Asnjë gate nuk është shënuar Passed nga ky audit.
A9: S3-A07 | B9: S3 | C9: P0 | D9: In Review | E9: Kryer në kod — pret pranim/gate | F9: Programmer A | G9: Programmer B | H9: Implement content items and immutable versions | I9: Mbeten concurrency test për dy writer-a në endpoint, verifikim i published-version me provider fixture dhe RG-06. Historia caption para 0009 nuk mund të rikonstruktohet si snapshot i plotë dhe shënohet legacy. | J9: RG-06 | K9: Prova e kërkuar nga backlog-u: Domain/DB/version concurrency tests Kriteri për t'u verifikuar (nuk deklarohet i kaluar): Published/approved version never mutated; edit creates new version as required; version belongs to same brand as refs. DA-07: Ndrysho fotografi/tekst/kanal pas miratimit; versioni i vjetër mbetet identik dhe approval i vjetër nuk autorizon versionin e ri; provo konkurencën. Pranimi kërkon edhe gate-et: RG-06. Asnjë gate nuk është shënuar Passed nga ky audit.
A10: S3-B02 | B10: S3 | C10: P0 | D10: In Review | E10: Kryer në kod — pret pranim/gate | F10: Programmer B | G10: Programmer A | H10: Build manual/custom post editor | I10: Mbeten fault/browser matrix më e plotë, composer me më shumë se një asset dhe pranimi RG-06/RG-14. | J10: RG-06,RG-14 | K10: Prova e kërkuar nga backlog-u: E2E draft/version tests Kriteri për t'u verifikuar (nuk deklarohet i kaluar): Draft survives refresh/fault; save conflict is explicit; invalid target/format combinations cannot be submitted. DA-16: Foto katrore/portrait/landscape në të dy kanalet: krahaso preview me dimensionet e asset-it të dërguar; golden render për composer kur zbatohet. Pranimi kërkon edhe gate-et: RG-06,RG-14. Asnjë gate nuk është shënuar Passed nga ky audit.
A11: S4-A04 | B11: S4 | C11: P0 | D11: In Review | E11: Kryer në kod — pret pranim/gate | F11: Programmer A | G11: Programmer B | H11: Implement Meta publisher adapter | I11: Mbeten Meta staging publish me llogari të autorizuar, public HTTPS/media expiry live dhe matrica e plotë për Instagram/provider errors. | J11: RG-04,RG-07 | K11: Prova e kërkuar nga backlog-u: Meta test account publish + mocks Kriteri për t'u verifikuar (nuk deklarohet i kaluar): Successful staging publish creates one expected post; media URL expires; unsupported capability fails before remote call. DA-01: Fixture: job i krijuar dje, container i krijuar tani, IN_PROGRESS pastaj FINISHED; publikim vetëm një herë. Provo veçmas skadimin real të container-it. DA-14: Facebook dhe Instagram: sukses, 429, 5xx, crash, expired token, cancel, timeout-after-write dhe dy worker-a; arkivo provider IDs pa tokenë. Pranimi kërkon edhe gate-et: RG-04,RG-07. Asnjë gate nuk është shënuar Passed nga ky audit.
A12: S4-A05 | B12: S4 | C12: P0 | D12: In Review | E12: Kryer në kod — pret pranim/gate | F12: Programmer A | G12: Programmer B | H12: Implement retry/backoff error taxonomy | I12: Mbeten Retry-After, exponential backoff/jitter, attempt limits dhe taxonomy fixtures për 429/5xx/network/auth/media. | J12: RG-07 | K12: Prova e kërkuar nga backlog-u: Fault fixtures for each class Kriteri për t'u verifikuar (nuk deklarohet i kaluar): Retry-After honored; revoked token never endless-retries; terminal error has stable code/remediation. DA-01: Fixture: job i krijuar dje, container i krijuar tani, IN_PROGRESS pastaj FINISHED; publikim vetëm një herë. Provo veçmas skadimin real të container-it. Pranimi kërkon edhe gate-et: RG-07. Asnjë gate nuk është shënuar Passed nga ky audit.
... A151: S1-B09 | B151: S1 | C151: P2 | D151: Not Started | E151: Pa filluar | F151: Programmer B | G151: Programmer A | H151: Define privacy-safe product event taxonomy | I151: Përcakto schema eventesh për onboarding/activation, IDs pseudonime dhe environment; zbato wrapper me allowlist dhe teste që refuzojnë email/tekst/post/prompt në payload. | J151: RG-09 | K151: Prova e kërkuar nga backlog-u: Event payload unit tests Kriteri për t'u verifikuar (nuk deklarohet i kaluar): Events have stable schema, org/user pseudonymous IDs, environment tag; forbidden properties tested. Pranimi kërkon edhe gate-et: RG-09. Asnjë gate nuk është shënuar Passed nga ky audit.
